{"version": 0.6, "generator": "Overpass API 0.7.62.5 1bd436f1", "osm3s": {"timestamp_osm_base": "2025-05-24T01:22:54Z", "copyright": "The data included in this document is from www.openstreetmap.org. The data is made available under ODbL."}, "elements": [{"type": "node", "id": 794246429, "lat": -2.9357266, "lon": -79.2525129}, {"type": "node", "id": 794247208, "lat": -2.9383451, "lon": -79.2492244}, {"type": "node", "id": 1067953507, "lat": -2.9227745, "lon": -79.2585954}, {"type": "node", "id": 1440344579, "lat": -2.9097, "lon": -79.28083}, {"type": "node", "id": 1440344582, "lat": -2.909582, "lon": -79.28203}, {"type": "node", "id": 1440344584, "lat": -2.908996, "lon": -79.282068}, {"type": "node", "id": 1440344595, "lat": -2.904604, "lon": -79.28579}, {"type": "node", "id": 1440344599, "lat": -2.90282, "lon": -79.285893}, {"type": "node", "id": 1440344600, "lat": -2.902404, "lon": -79.286318}, {"type": "node", "id": 1440344603, "lat": -2.900824, "lon": -79.287091}, {"type": "node", "id": 1505886353, "lat": -2.910316, "lon": -79.278879}, {"type": "node", "id": 1505886357, "lat": -2.909414, "lon": -79.27808}, {"type": "node", "id": 1505886367, "lat": -2.910301, "lon": -79.272344}, {"type": "node", "id": 1505886372, "lat": -2.910077, "lon": -79.268118}, {"type": "node", "id": 1505886376, "lat": -2.911101, "lon": -79.266761}, {"type": "node", "id": 1505886378, "lat": -2.911696, "lon": -79.2671991}, {"type": "node", "id": 1505886385, "lat": -2.910955, "lon": -79.266212}, {"type": "node", "id": 1505886387, "lat": -2.909873, "lon": -79.266709}, {"type": "node", "id": 1505886389, "lat": -2.909573, "lon": -79.266139}, {"type": "node", "id": 1505886391, "lat": -2.909098, "lon": -79.266167}, {"type": "node", "id": 1505886394, "lat": -2.908546, "lon": -79.265869}, {"type": "node", "id": 1505886397, "lat": -2.907014, "lon": -79.266117}, {"type": "node", "id": 1505886401, "lat": -2.906566, "lon": -79.265603}, {"type": "node", "id": 1505886403, "lat": -2.907015, "lon": -79.26455}, {"type": "node", "id": 1505886406, "lat": -2.90776, "lon": -79.264012}, {"type": "node", "id": 1505886408, "lat": -2.907182, "lon": -79.262725}, {"type": "node", "id": 1505886411, "lat": -2.906769, "lon": -79.262424}, {"type": "node", "id": 1505886413, "lat": -2.905024, "lon": -79.262556}, {"type": "node", "id": 1505886423, "lat": -2.902201, "lon": -79.260506}, {"type": "node", "id": 1505886425, "lat": -2.903137, "lon": -79.2599003}, {"type": "node", "id": 1505886427, "lat": -2.9035863, "lon": -79.2597066}, {"type": "node", "id": 1505886433, "lat": -2.9046, "lon": -79.259493}, {"type": "node", "id": 1505886436, "lat": -2.905294, "lon": -79.258767}, {"type": "node", "id": 1505886442, "lat": -2.907695, "lon": -79.259136}, {"type": "node", "id": 1505886445, "lat": -2.908474, "lon": -79.258908}, {"type": "node", "id": 1505886447, "lat": -2.907975, "lon": -79.258471}, {"type": "node", "id": 1505886449, "lat": -2.907889, "lon": -79.258124}, {"type": "node", "id": 1505886450, "lat": -2.908147, "lon": -79.257576}, {"type": "node", "id": 1505886460, "lat": -2.913139, "lon": -79.259544}, {"type": "node", "id": 1505886462, "lat": -2.914488, "lon": -79.259304}, {"type": "node", "id": 1505886469, "lat": -2.919482, "lon": -79.25866}, {"type": "node", "id": 1505886472, "lat": -2.921744, "lon": -79.258704}, {"type": "node", "id": 1505886475, "lat": -2.923013, "lon": -79.258384}, {"type": "node", "id": 1505886476, "lat": -2.923489, "lon": -79.258131}, {"type": "node", "id": 1505886478, "lat": -2.924133, "lon": -79.257038}, {"type": "node", "id": 1505886479, "lat": -2.924439, "lon": -79.256766}, {"type": "node", "id": 1505886481, "lat": -2.924959, "lon": -79.256526}, {"type": "node", "id": 1505886488, "lat": -2.930781, "lon": -79.253901}, {"type": "node", "id": 1505886493, "lat": -2.933704, "lon": -79.253682}, {"type": "node", "id": 1505886494, "lat": -2.934295, "lon": -79.253648}, {"type": "node", "id": 1505886496, "lat": -2.935364, "lon": -79.253081}, {"type": "node", "id": 6203419317, "lat": -2.8742987, "lon": -79.3003759}, {"type": "node", "id": 6203419332, "lat": -2.8757935, "lon": -79.2999923}, {"type": "node", "id": 6203419493, "lat": -2.878759, "lon": -79.3010303}, {"type": "node", "id": 6203419495, "lat": -2.8788688, "lon": -79.3011779}, {"type": "node", "id": 6203419499, "lat": -2.8793644, "lon": -79.3015775}, {"type": "node", "id": 6203419502, "lat": -2.8798707, "lon": -79.3018162}, {"type": "node", "id": 6778360224, "lat": -2.7462435, "lon": -79.2157463}, {"type": "node", "id": 6778360225, "lat": -2.7461916, "lon": -79.217347}, {"type": "node", "id": 6778360226, "lat": -2.7460506, "lon": -79.219805}, {"type": "node", "id": 6778360227, "lat": -2.7459719, "lon": -79.2216059}, {"type": "node", "id": 6778360228, "lat": -2.745911, "lon": -79.2232067}, {"type": "node", "id": 6778360229, "lat": -2.7458861, "lon": -79.2246641}, {"type": "node", "id": 6778360230, "lat": -2.7457436, "lon": -79.226179}, {"type": "node", "id": 6778360231, "lat": -2.7459083, "lon": -79.2274743}, {"type": "node", "id": 6778360232, "lat": -2.7471286, "lon": -79.2271184}, {"type": "node", "id": 6778360233, "lat": -2.7480062, "lon": -79.227465}, {"type": "node", "id": 6778360234, "lat": -2.7484681, "lon": -79.2279673}, {"type": "node", "id": 6778360235, "lat": -2.7490384, "lon": -79.2283341}, {"type": "node", "id": 6778360236, "lat": -2.7499978, "lon": -79.2289689}, {"type": "node", "id": 6778360237, "lat": -2.7505231, "lon": -79.2294902}, {"type": "node", "id": 6778360238, "lat": -2.7509939, "lon": -79.2298959}, {"type": "node", "id": 6778360239, "lat": -2.7516008, "lon": -79.230611}, {"type": "node", "id": 6778360240, "lat": -2.7517381, "lon": -79.2316748}, {"type": "node", "id": 6778360241, "lat": -2.7516946, "lon": -79.2328743}, {"type": "node", "id": 6778360242, "lat": -2.7519946, "lon": -79.2339186}, {"type": "node", "id": 6778360243, "lat": -2.7523846, "lon": -79.2347111}, {"type": "node", "id": 6778360244, "lat": -2.7534534, "lon": -79.2358511}, {"type": "node", "id": 6778360245, "lat": -2.7538069, "lon": -79.2364306}, {"type": "node", "id": 6778360246, "lat": -2.7541153, "lon": -79.2370495}, {"type": "node", "id": 6778360247, "lat": -2.754388, "lon": -79.2380551}, {"type": "node", "id": 6778360248, "lat": -2.754507, "lon": -79.2390026}, {"type": "node", "id": 6778360249, "lat": -2.7550508, "lon": -79.2398533}, {"type": "node", "id": 6778360250, "lat": -2.7560931, "lon": -79.2414688}, {"type": "node", "id": 6778360251, "lat": -2.7564287, "lon": -79.2421455}, {"type": "node", "id": 6778360252, "lat": -2.7568002, "lon": -79.2426289}, {"type": "node", "id": 6778360253, "lat": -2.7574434, "lon": -79.243421}, {"type": "node", "id": 6778360254, "lat": -2.7583758, "lon": -79.2440969}, {"type": "node", "id": 6778360255, "lat": -2.7592178, "lon": -79.2448112}, {"type": "node", "id": 6778360256, "lat": -2.7598794, "lon": -79.2457584}, {"type": "node", "id": 6778360257, "lat": -2.7611644, "lon": -79.2464141}, {"type": "node", "id": 6778360258, "lat": -2.7623674, "lon": -79.2466057}, {"type": "node", "id": 6778360259, "lat": -2.7637509, "lon": -79.2465654}, {"type": "node", "id": 6778360260, "lat": -2.7646821, "lon": -79.246473}, {"type": "node", "id": 6778360261, "lat": -2.7654867, "lon": -79.2463291}, {"type": "node", "id": 6778360262, "lat": -2.7666437, "lon": -79.2460132}, {"type": "node", "id": 6778360263, "lat": -2.7672128, "lon": -79.2456122}, {"type": "node", "id": 6778360264, "lat": -2.7677909, "lon": -79.2451538}, {"type": "node", "id": 6778360265, "lat": -2.76836, "lon": -79.2447815}, {"type": "node", "id": 6778360266, "lat": -2.7691101, "lon": -79.2444656}, {"type": "node", "id": 6778360267, "lat": -2.7697693, "lon": -79.2438076}, {"type": "node", "id": 6778360268, "lat": -2.7702562, "lon": -79.2429205}, {"type": "node", "id": 6778360269, "lat": -2.771032, "lon": -79.2416503}, {"type": "node", "id": 6778360270, "lat": -2.7715194, "lon": -79.2409914}, {"type": "node", "id": 6778360271, "lat": -2.7720161, "lon": -79.2405652}, {"type": "node", "id": 6778360272, "lat": -2.7729919, "lon": -79.2400416}, {"type": "node", "id": 6778360273, "lat": -2.7743752, "lon": -79.2398844}, {"type": "node", "id": 6778360274, "lat": -2.7753703, "lon": -79.2401409}, {"type": "node", "id": 6778360275, "lat": -2.776004, "lon": -79.2405969}, {"type": "node", "id": 6778360276, "lat": -2.7773438, "lon": -79.2415808}, {"type": "node", "id": 6778360277, "lat": -2.7771189, "lon": -79.242404}, {"type": "node", "id": 6778360278, "lat": -2.7767039, "lon": -79.243042}, {"type": "node", "id": 6778360279, "lat": -2.7761621, "lon": -79.2435756}, {"type": "node", "id": 6778360280, "lat": -2.7760999, "lon": -79.244249}, {"type": "node", "id": 6778360281, "lat": -2.7761552, "lon": -79.2449662}, {"type": "node", "id": 6778360282, "lat": -2.7760206, "lon": -79.2457122}, {"type": "node", "id": 6778360283, "lat": -2.7761121, "lon": -79.2463691}, {"type": "node", "id": 6778360284, "lat": -2.7767273, "lon": -79.2465992}, {"type": "node", "id": 6778373985, "lat": -2.776828, "lon": -79.2474433}, {"type": "node", "id": 6778373991, "lat": -2.7761226, "lon": -79.2478401}, {"type": "node", "id": 6778373992, "lat": -2.7759566, "lon": -79.2482828}, {"type": "node", "id": 6778373993, "lat": -2.7760361, "lon": -79.2493146}, {"type": "node", "id": 6778373997, "lat": -2.7758749, "lon": -79.2505868}, {"type": "node", "id": 6778373998, "lat": -2.7752087, "lon": -79.2522682}, {"type": "node", "id": 6778373999, "lat": -2.7751708, "lon": -79.2531842}, {"type": "node", "id": 6778374000, "lat": -2.775154, "lon": -79.2534482}, {"type": "node", "id": 6778374001, "lat": -2.7748684, "lon": -79.2543604}, {"type": "node", "id": 6778374003, "lat": -2.7749891, "lon": -79.2561753}, {"type": "node", "id": 6778374004, "lat": -2.7756908, "lon": -79.2566415}, {"type": "node", "id": 6778374005, "lat": -2.776129, "lon": -79.2571631}, {"type": "node", "id": 6778374006, "lat": -2.7766188, "lon": -79.2572027}, {"type": "node", "id": 6778374007, "lat": -2.7766867, "lon": -79.2576576}, {"type": "node", "id": 6778374008, "lat": -2.7767221, "lon": -79.2580856}, {"type": "node", "id": 6778374009, "lat": -2.7769341, "lon": -79.2584556}, {"type": "node", "id": 6778374010, "lat": -2.7770251, "lon": -79.2594365}, {"type": "node", "id": 6778374012, "lat": -2.7770082, "lon": -79.2598023}, {"type": "node", "id": 6778374015, "lat": -2.7772455, "lon": -79.261171}, {"type": "node", "id": 6778374017, "lat": -2.7783848, "lon": -79.2623687}, {"type": "node", "id": 6778374018, "lat": -2.7793657, "lon": -79.2633585}, {"type": "node", "id": 6778374019, "lat": -2.7801884, "lon": -79.2637138}, {"type": "node", "id": 6778374021, "lat": -2.7811095, "lon": -79.2640132}, {"type": "node", "id": 6778374023, "lat": -2.7819634, "lon": -79.264633}, {"type": "node", "id": 6778374025, "lat": -2.7830321, "lon": -79.2651747}, {"type": "node", "id": 6778374026, "lat": -2.7844887, "lon": -79.2658326}, {"type": "node", "id": 6778374027, "lat": -2.7860247, "lon": -79.2665902}, {"type": "node", "id": 6778374029, "lat": -2.787035, "lon": -79.2668945}, {"type": "node", "id": 6778374031, "lat": -2.7880864, "lon": -79.2678283}, {"type": "node", "id": 6778374033, "lat": -2.7894541, "lon": -79.2687075}, {"type": "node", "id": 6778374035, "lat": -2.7901684, "lon": -79.2696777}, {"type": "node", "id": 6778374036, "lat": -2.7900431, "lon": -79.2712325}, {"type": "node", "id": 6778374039, "lat": -2.7909312, "lon": -79.2718564}, {"type": "node", "id": 6778374040, "lat": -2.7916071, "lon": -79.2722817}, {"type": "node", "id": 6778374041, "lat": -2.7926361, "lon": -79.2720511}, {"type": "node", "id": 6778374042, "lat": -2.7936, "lon": -79.2725399}, {"type": "node", "id": 6778374043, "lat": -2.7941294, "lon": -79.272914}, {"type": "node", "id": 6778374044, "lat": -2.7945634, "lon": -79.2743177}, {"type": "node", "id": 6778374045, "lat": -2.7950508, "lon": -79.2744752}, {"type": "node", "id": 6778374046, "lat": -2.7953935, "lon": -79.2745425}, {"type": "node", "id": 6778374047, "lat": -2.7958774, "lon": -79.2738053}, {"type": "node", "id": 6778374048, "lat": -2.7964915, "lon": -79.2729404}, {"type": "node", "id": 6778374051, "lat": -2.796742, "lon": -79.2720527}, {"type": "node", "id": 6778374052, "lat": -2.797066, "lon": -79.271204}, {"type": "node", "id": 6778374054, "lat": -2.7973303, "lon": -79.2706919}, {"type": "node", "id": 6778374055, "lat": -2.7974512, "lon": -79.2704009}, {"type": "node", "id": 6778374056, "lat": -2.797756, "lon": -79.2694557}, {"type": "node", "id": 6778374057, "lat": -2.7975036, "lon": -79.2684446}, {"type": "node", "id": 6778374058, "lat": -2.7972897, "lon": -79.2672185}, {"type": "node", "id": 6778374059, "lat": -2.7975563, "lon": -79.2667354}, {"type": "node", "id": 6778374060, "lat": -2.7985179, "lon": -79.2657284}, {"type": "node", "id": 6778374061, "lat": -2.8023087, "lon": -79.2688416}, {"type": "node", "id": 6778374064, "lat": -2.8025782, "lon": -79.2690871}, {"type": "node", "id": 6778374065, "lat": -2.8052859, "lon": -79.2718605}, {"type": "node", "id": 6778374066, "lat": -2.8052692, "lon": -79.2727463}, {"type": "node", "id": 6778374067, "lat": -2.8053697, "lon": -79.2734308}, {"type": "node", "id": 6778374068, "lat": -2.8058678, "lon": -79.2739382}, {"type": "node", "id": 6778374069, "lat": -2.8052715, "lon": -79.2743179}, {"type": "node", "id": 6778374070, "lat": -2.805137, "lon": -79.2750915}, {"type": "node", "id": 6778374071, "lat": -2.8049217, "lon": -79.2762655}, {"type": "node", "id": 6778374072, "lat": -2.80515, "lon": -79.2777479}, {"type": "node", "id": 6778374073, "lat": -2.805558, "lon": -79.278514}, {"type": "node", "id": 6778374074, "lat": -2.8065816, "lon": -79.2796423}, {"type": "node", "id": 6778374075, "lat": -2.8075138, "lon": -79.2801721}, {"type": "node", "id": 6778374076, "lat": -2.8089336, "lon": -79.2802335}, {"type": "node", "id": 6778374077, "lat": -2.8086452, "lon": -79.2809276}, {"type": "node", "id": 6778374078, "lat": -2.8076786, "lon": -79.2815978}, {"type": "node", "id": 6778374079, "lat": -2.807137, "lon": -79.282263}, {"type": "node", "id": 6778374080, "lat": -2.8063146, "lon": -79.2825885}, {"type": "node", "id": 6778374081, "lat": -2.8054836, "lon": -79.2832288}, {"type": "node", "id": 6778374082, "lat": -2.8052772, "lon": -79.2842892}, {"type": "node", "id": 6778374083, "lat": -2.8054596, "lon": -79.2853148}, {"type": "node", "id": 6778374084, "lat": -2.8055603, "lon": -79.2861993}, {"type": "node", "id": 6778374085, "lat": -2.806331, "lon": -79.2875883}, {"type": "node", "id": 6778374086, "lat": -2.8067218, "lon": -79.2888687}, {"type": "node", "id": 6778374087, "lat": -2.807095, "lon": -79.2905488}, {"type": "node", "id": 6778374088, "lat": -2.8068257, "lon": -79.291924}, {"type": "node", "id": 6778374089, "lat": -2.8070262, "lon": -79.2929777}, {"type": "node", "id": 6778374090, "lat": -2.8120087, "lon": -79.2928513}, {"type": "node", "id": 6778374091, "lat": -2.8126247, "lon": -79.2935563}, {"type": "node", "id": 6778374092, "lat": -2.8129513, "lon": -79.2942664}, {"type": "node", "id": 6778374093, "lat": -2.8130699, "lon": -79.2950076}, {"type": "node", "id": 6778374094, "lat": -2.8138032, "lon": -79.2955973}, {"type": "node", "id": 6778374095, "lat": -2.8145451, "lon": -79.2958356}, {"type": "node", "id": 6778374096, "lat": -2.8152142, "lon": -79.3019137}, {"type": "node", "id": 6778374097, "lat": -2.8220223, "lon": -79.3072505}, {"type": "node", "id": 6778374098, "lat": -2.8254119, "lon": -79.3123304}, {"type": "node", "id": 6778374099, "lat": -2.8234054, "lon": -79.3130921}, {"type": "node", "id": 6778374100, "lat": -2.8228452, "lon": -79.3134223}, {"type": "node", "id": 6778374101, "lat": -2.8223576, "lon": -79.3139132}, {"type": "node", "id": 6778374102, "lat": -2.8216703, "lon": -79.3139001}, {"type": "node", "id": 6778374103, "lat": -2.8209116, "lon": -79.3145274}, {"type": "node", "id": 6778374104, "lat": -2.8199169, "lon": -79.3145715}, {"type": "node", "id": 6778374105, "lat": -2.8188775, "lon": -79.3149676}, {"type": "node", "id": 6778374106, "lat": -2.8189876, "lon": -79.316045}, {"type": "node", "id": 6778374107, "lat": -2.8185542, "lon": -79.3164576}, {"type": "node", "id": 6778374108, "lat": -2.8182565, "lon": -79.3169954}, {"type": "node", "id": 6778374109, "lat": -2.8181764, "lon": -79.317864}, {"type": "node", "id": 6778374110, "lat": -2.8177883, "lon": -79.3183676}, {"type": "node", "id": 6778374111, "lat": -2.8172733, "lon": -79.3186882}, {"type": "node", "id": 6778374112, "lat": -2.817021, "lon": -79.3193175}, {"type": "node", "id": 6778374113, "lat": -2.817284, "lon": -79.319854}, {"type": "node", "id": 6778374114, "lat": -2.8179446, "lon": -79.3201841}, {"type": "node", "id": 6778374115, "lat": -2.8185056, "lon": -79.3203997}, {"type": "node", "id": 6778374116, "lat": -2.8190758, "lon": -79.320753}, {"type": "node", "id": 6778374117, "lat": -2.8194113, "lon": -79.3213467}, {"type": "node", "id": 6778374118, "lat": -2.8193309, "lon": -79.3220438}, {"type": "node", "id": 6778374119, "lat": -2.8189793, "lon": -79.3227531}, {"type": "node", "id": 6778374120, "lat": -2.818727, "lon": -79.3233931}, {"type": "node", "id": 6778374121, "lat": -2.8190896, "lon": -79.3240211}, {"type": "node", "id": 6778374122, "lat": -2.8192714, "lon": -79.3246723}, {"type": "node", "id": 6778374123, "lat": -2.8190099, "lon": -79.3252095}, {"type": "node", "id": 6778374124, "lat": -2.8185315, "lon": -79.3257936}, {"type": "node", "id": 6778374125, "lat": -2.818089, "lon": -79.3262175}, {"type": "node", "id": 6778374126, "lat": -2.8176285, "lon": -79.3267212}, {"type": "node", "id": 6778374127, "lat": -2.8172675, "lon": -79.3272361}, {"type": "node", "id": 6778374128, "lat": -2.8169881, "lon": -79.3278649}, {"type": "node", "id": 6778374129, "lat": -2.8168535, "lon": -79.3285509}, {"type": "node", "id": 6778374130, "lat": -2.8171172, "lon": -79.3296016}, {"type": "node", "id": 6778374131, "lat": -2.8175253, "lon": -79.3303779}, {"type": "node", "id": 6778374132, "lat": -2.817879, "lon": -79.3310968}, {"type": "node", "id": 6778374133, "lat": -2.8186768, "lon": -79.332524}, {"type": "node", "id": 6778374134, "lat": -2.8190213, "lon": -79.3331171}, {"type": "node", "id": 6778374135, "lat": -2.8193928, "lon": -79.3336309}, {"type": "node", "id": 6778374136, "lat": -2.8199812, "lon": -79.334041}, {"type": "node", "id": 6778374137, "lat": -2.8202443, "lon": -79.3346117}, {"type": "node", "id": 6778374138, "lat": -2.819983, "lon": -79.3352866}, {"type": "node", "id": 6778374139, "lat": -2.8199839, "lon": -79.335892}, {"type": "node", "id": 6778374140, "lat": -2.8197317, "lon": -79.3366124}, {"type": "node", "id": 6778374141, "lat": -2.8189729, "lon": -79.3371857}, {"type": "node", "id": 6778374142, "lat": -2.8183135, "lon": -79.3377009}, {"type": "node", "id": 6778374143, "lat": -2.8177807, "lon": -79.3382509}, {"type": "node", "id": 6778374144, "lat": -2.81742, "lon": -79.3389714}, {"type": "node", "id": 6778374145, "lat": -2.8170599, "lon": -79.3400692}, {"type": "node", "id": 6778374146, "lat": -2.8168801, "lon": -79.3407895}, {"type": "node", "id": 6778374147, "lat": -2.8166642, "lon": -79.3416127}, {"type": "node", "id": 6778374148, "lat": -2.8165475, "lon": -79.3422183}, {"type": "node", "id": 6778374149, "lat": -2.8164401, "lon": -79.3430071}, {"type": "node", "id": 6778374150, "lat": -2.8163777, "lon": -79.3436131}, {"type": "node", "id": 6778374151, "lat": -2.8162798, "lon": -79.3447672}, {"type": "node", "id": 6778374152, "lat": -2.8162448, "lon": -79.345579}, {"type": "node", "id": 6778374153, "lat": -2.8163723, "lon": -79.3461842}, {"type": "node", "id": 6778374154, "lat": -2.8167349, "lon": -79.3467778}, {"type": "node", "id": 6778374155, "lat": -2.8171244, "lon": -79.3472455}, {"type": "node", "id": 6778374156, "lat": -2.8177129, "lon": -79.3477466}, {"type": "node", "id": 6778374157, "lat": -2.8183918, "lon": -79.3482139}, {"type": "node", "id": 6778374158, "lat": -2.8189077, "lon": -79.3485212}, {"type": "node", "id": 6778374159, "lat": -2.8196226, "lon": -79.3488631}, {"type": "node", "id": 6778374160, "lat": -2.8201836, "lon": -79.349113}, {"type": "node", "id": 6778374161, "lat": -2.8206547, "lon": -79.3496492}, {"type": "node", "id": 6778374162, "lat": -2.8212252, "lon": -79.3501964}, {"type": "node", "id": 6778374163, "lat": -2.821696, "lon": -79.3505954}, {"type": "node", "id": 6778374164, "lat": -2.8222843, "lon": -79.3509257}, {"type": "node", "id": 6778374165, "lat": -2.8231981, "lon": -79.3512324}, {"type": "node", "id": 6778374166, "lat": -2.8238311, "lon": -79.3512197}, {"type": "node", "id": 6778374167, "lat": -2.8244277, "lon": -79.3510699}, {"type": "node", "id": 6778374168, "lat": -2.8250604, "lon": -79.3507942}, {"type": "node", "id": 6778374169, "lat": -2.825702, "lon": -79.3505077}, {"type": "node", "id": 6778374170, "lat": -2.8264884, "lon": -79.3502087}, {"type": "node", "id": 6778374171, "lat": -2.8271663, "lon": -79.3499789}, {"type": "node", "id": 6778374172, "lat": -2.8278081, "lon": -79.3497948}, {"type": "node", "id": 6778374173, "lat": -2.8287576, "lon": -79.3497811}, {"type": "node", "id": 6778374174, "lat": -2.8294632, "lon": -79.3498942}, {"type": "node", "id": 6778374175, "lat": -2.8303313, "lon": -79.3499267}, {"type": "node", "id": 6778374176, "lat": -2.8309648, "lon": -79.3501995}, {"type": "node", "id": 6778374177, "lat": -2.832176, "lon": -79.3497639}, {"type": "node", "id": 6778374178, "lat": -2.8327994, "lon": -79.3493864}, {"type": "node", "id": 6778374179, "lat": -2.8347338, "lon": -79.3487625}, {"type": "node", "id": 6778374180, "lat": -2.8362431, "lon": -79.3481201}, {"type": "node", "id": 6778374181, "lat": -2.8376442, "lon": -79.3477606}, {"type": "node", "id": 6778374182, "lat": -2.8385122, "lon": -79.3476464}, {"type": "node", "id": 6778374183, "lat": -2.8394613, "lon": -79.3473252}, {"type": "node", "id": 6778374184, "lat": -2.8405088, "lon": -79.3462793}, {"type": "node", "id": 6778374185, "lat": -2.8414757, "lon": -79.3457321}, {"type": "node", "id": 6778374186, "lat": -2.8420086, "lon": -79.3453171}, {"type": "node", "id": 6778374187, "lat": -2.8424782, "lon": -79.3448836}, {"type": "node", "id": 6778374188, "lat": -2.8433273, "lon": -79.3441668}, {"type": "node", "id": 6778374189, "lat": -2.8441953, "lon": -79.3440717}, {"type": "node", "id": 6778374190, "lat": -2.8447829, "lon": -79.3439387}, {"type": "node", "id": 6778374191, "lat": -2.8454069, "lon": -79.3439193}, {"type": "node", "id": 6778374192, "lat": -2.8464461, "lon": -79.3434097}, {"type": "node", "id": 6778374193, "lat": -2.8465808, "lon": -79.3427316}, {"type": "node", "id": 6778374194, "lat": -2.8464891, "lon": -79.3418469}, {"type": "node", "id": 6778374195, "lat": -2.8462978, "lon": -79.3409056}, {"type": "node", "id": 6778374196, "lat": -2.8460878, "lon": -79.339513}, {"type": "node", "id": 6778374197, "lat": -2.8467294, "lon": -79.3391731}, {"type": "node", "id": 6778374198, "lat": -2.8473177, "lon": -79.3395489}, {"type": "node", "id": 6778374199, "lat": -2.8482131, "lon": -79.3396612}, {"type": "node", "id": 6778374200, "lat": -2.8484943, "lon": -79.3402544}, {"type": "node", "id": 6778374201, "lat": -2.8486581, "lon": -79.3409512}, {"type": "node", "id": 6778374202, "lat": -2.8488763, "lon": -79.3417018}, {"type": "node", "id": 6778374203, "lat": -2.8498562, "lon": -79.3439529}, {"type": "node", "id": 6778374204, "lat": -2.8502369, "lon": -79.3446173}, {"type": "node", "id": 6778374205, "lat": -2.8506993, "lon": -79.3453789}, {"type": "node", "id": 6778374206, "lat": -2.8510799, "lon": -79.3459719}, {"type": "node", "id": 6778374207, "lat": -2.8514243, "lon": -79.3464757}, {"type": "node", "id": 6778374208, "lat": -2.851923, "lon": -79.3473637}, {"type": "node", "id": 6778374209, "lat": -2.8523041, "lon": -79.3482878}, {"type": "node", "id": 6778374210, "lat": -2.8529106, "lon": -79.3486973}, {"type": "node", "id": 6778374211, "lat": -2.8532915, "lon": -79.3494399}, {"type": "node", "id": 6778374212, "lat": -2.8530665, "lon": -79.3502205}, {"type": "node", "id": 6778374213, "lat": -2.8532572, "lon": -79.3507879}, {"type": "node", "id": 6778374214, "lat": -2.8534215, "lon": -79.351826}, {"type": "node", "id": 6778374215, "lat": -2.8539379, "lon": -79.3524312}, {"type": "node", "id": 6778374216, "lat": -2.8541741, "lon": -79.3532167}, {"type": "node", "id": 6778374217, "lat": -2.8610289, "lon": -79.3595236}, {"type": "node", "id": 6778374218, "lat": -2.8617262, "lon": -79.3602034}, {"type": "node", "id": 6778374219, "lat": -2.8622788, "lon": -79.3608266}, {"type": "node", "id": 6778374220, "lat": -2.8628585, "lon": -79.3615289}, {"type": "node", "id": 6778374221, "lat": -2.863357, "lon": -79.3622596}, {"type": "node", "id": 6778374222, "lat": -2.8639914, "lon": -79.3632098}, {"type": "node", "id": 6778374223, "lat": -2.8645438, "lon": -79.3637223}, {"type": "node", "id": 6778374224, "lat": -2.8647979, "lon": -79.3643498}, {"type": "node", "id": 6778374225, "lat": -2.864971, "lon": -79.3652524}, {"type": "node", "id": 6778374226, "lat": -2.8653156, "lon": -79.3659028}, {"type": "node", "id": 6778374227, "lat": -2.8659412, "lon": -79.3670414}, {"type": "node", "id": 6778374228, "lat": -2.8665216, "lon": -79.3682194}, {"type": "node", "id": 6778374229, "lat": -2.8671292, "lon": -79.3693625}, {"type": "node", "id": 6778374230, "lat": -2.8677094, "lon": -79.3703977}, {"type": "node", "id": 6778374231, "lat": -2.8682085, "lon": -79.3715758}, {"type": "node", "id": 6778374232, "lat": -2.8686806, "lon": -79.3728618}, {"type": "node", "id": 6778374233, "lat": -2.8690078, "lon": -79.3740048}, {"type": "node", "id": 6778374234, "lat": -2.8691539, "lon": -79.3750052}, {"type": "node", "id": 6778374235, "lat": -2.8691373, "lon": -79.3760598}, {"type": "node", "id": 6778374236, "lat": -2.8690659, "lon": -79.3767237}, {"type": "node", "id": 6778374237, "lat": -2.8689586, "lon": -79.3775918}, {"type": "node", "id": 6778374238, "lat": -2.8692948, "lon": -79.3786898}, {"type": "node", "id": 6778374239, "lat": -2.8700378, "lon": -79.3797355}, {"type": "node", "id": 6778374240, "lat": -2.8704277, "lon": -79.3804247}, {"type": "node", "id": 6778374241, "lat": -2.8707093, "lon": -79.3813434}, {"type": "node", "id": 6778374242, "lat": -2.871253, "lon": -79.3821088}, {"type": "node", "id": 6778374243, "lat": -2.8714799, "lon": -79.3826706}, {"type": "node", "id": 6778374244, "lat": -2.8716346, "lon": -79.3833343}, {"type": "node", "id": 6778374245, "lat": -2.8717895, "lon": -79.3841767}, {"type": "node", "id": 6778374246, "lat": -2.8717452, "lon": -79.3848154}, {"type": "node", "id": 6778374247, "lat": -2.8715381, "lon": -79.3854284}, {"type": "node", "id": 6778374248, "lat": -2.8742876, "lon": -79.3856803}, {"type": "node", "id": 6778374249, "lat": -2.8749023, "lon": -79.3855007}, {"type": "node", "id": 6778374250, "lat": -2.8763493, "lon": -79.3855358}, {"type": "node", "id": 6778374251, "lat": -2.8776967, "lon": -79.3854934}, {"type": "node", "id": 6778374252, "lat": -2.8790441, "lon": -79.3854302}, {"type": "node", "id": 6778374253, "lat": -2.8806627, "lon": -79.3852857}, {"type": "node", "id": 6778374254, "lat": -2.881784, "lon": -79.3852842}, {"type": "node", "id": 6778374255, "lat": -2.8834937, "lon": -79.3856376}, {"type": "node", "id": 6778374256, "lat": -2.8851132, "lon": -79.3860862}, {"type": "node", "id": 6778374257, "lat": -2.8857458, "lon": -79.3857885}, {"type": "node", "id": 6778374258, "lat": -2.8860162, "lon": -79.3851838}, {"type": "node", "id": 6778374259, "lat": -2.8860063, "lon": -79.3845834}, {"type": "node", "id": 6778374260, "lat": -2.8856167, "lon": -79.3840881}, {"type": "node", "id": 6778374261, "lat": -2.8849921, "lon": -79.3836444}, {"type": "node", "id": 6778374262, "lat": -2.8843585, "lon": -79.3832124}, {"type": "node", "id": 6778374263, "lat": -2.8840141, "lon": -79.3826991}, {"type": "node", "id": 6778374264, "lat": -2.8835883, "lon": -79.3821977}, {"type": "node", "id": 6778374265, "lat": -2.8830633, "lon": -79.3818566}, {"type": "node", "id": 6778374266, "lat": -2.8824298, "lon": -79.3814983}, {"type": "node", "id": 6778374267, "lat": -2.8820853, "lon": -79.3809451}, {"type": "node", "id": 6778374268, "lat": -2.8814964, "lon": -79.3801904}, {"type": "node", "id": 6778374269, "lat": -2.8811881, "lon": -79.3795623}, {"type": "node", "id": 6778374270, "lat": -2.8807168, "lon": -79.3788581}, {"type": "node", "id": 6778374271, "lat": -2.8804806, "lon": -79.3781046}, {"type": "node", "id": 6778374272, "lat": -2.8801087, "lon": -79.377317}, {"type": "node", "id": 6778374273, "lat": -2.8796287, "lon": -79.3768499}, {"type": "node", "id": 6778374274, "lat": -2.8792388, "lon": -79.3761203}, {"type": "node", "id": 6778374275, "lat": -2.8790389, "lon": -79.3754347}, {"type": "node", "id": 6778374276, "lat": -2.8787667, "lon": -79.3747729}, {"type": "node", "id": 6778374277, "lat": -2.8782686, "lon": -79.3742946}, {"type": "node", "id": 6778374278, "lat": -2.8775621, "lon": -79.3735081}, {"type": "node", "id": 6778374279, "lat": -2.8783035, "lon": -79.3734255}, {"type": "node", "id": 6778374280, "lat": -2.8791533, "lon": -79.3732276}, {"type": "node", "id": 6778374281, "lat": -2.8797861, "lon": -79.373026}, {"type": "node", "id": 6778374282, "lat": -2.8806088, "lon": -79.3728764}, {"type": "node", "id": 6778374283, "lat": -2.8813412, "lon": -79.3727871}, {"type": "node", "id": 6778374284, "lat": -2.8819105, "lon": -79.3725334}, {"type": "node", "id": 6778374285, "lat": -2.8822353, "lon": -79.3719724}, {"type": "node", "id": 6778374286, "lat": -2.8827589, "lon": -79.3713078}, {"type": "node", "id": 6778374287, "lat": -2.8834908, "lon": -79.3709256}, {"type": "node", "id": 6778374288, "lat": -2.8841245, "lon": -79.3714312}, {"type": "node", "id": 6778374289, "lat": -2.8848126, "lon": -79.3719716}, {"type": "node", "id": 6778374290, "lat": -2.8857897, "lon": -79.3722462}, {"type": "node", "id": 6778374291, "lat": -2.8863046, "lon": -79.3718104}, {"type": "node", "id": 6778374292, "lat": -2.8869099, "lon": -79.3713969}, {"type": "node", "id": 6778374293, "lat": -2.8874974, "lon": -79.3712049}, {"type": "node", "id": 6778374294, "lat": -2.8884193, "lon": -79.3708405}, {"type": "node", "id": 6778374295, "lat": -2.8890786, "lon": -79.3702341}, {"type": "node", "id": 6778374296, "lat": -2.888924, "lon": -79.3696525}, {"type": "node", "id": 6778374297, "lat": -2.8883447, "lon": -79.3692547}, {"type": "node", "id": 6778374298, "lat": -2.8878104, "lon": -79.3687226}, {"type": "node", "id": 6778374299, "lat": -2.887764, "lon": -79.3679508}, {"type": "node", "id": 6778374300, "lat": -2.8879349, "lon": -79.3673154}, {"type": "node", "id": 6778374301, "lat": -2.8875631, "lon": -79.3666053}, {"type": "node", "id": 6778374302, "lat": -2.8872277, "lon": -79.3660454}, {"type": "node", "id": 6778374303, "lat": -2.8869372, "lon": -79.3652436}, {"type": "node", "id": 6778374304, "lat": -2.8861948, "lon": -79.3647011}, {"type": "node", "id": 6778374305, "lat": -2.8860041, "lon": -79.3640948}, {"type": "node", "id": 6778374306, "lat": -2.886184, "lon": -79.3634211}, {"type": "node", "id": 6778374307, "lat": -2.8864451, "lon": -79.3626719}, {"type": "node", "id": 6778374308, "lat": -2.8865252, "lon": -79.3617488}, {"type": "node", "id": 6778374309, "lat": -2.8862799, "lon": -79.3609773}, {"type": "node", "id": 6778374310, "lat": -2.8863873, "lon": -79.3602087}, {"type": "node", "id": 6778374311, "lat": -2.8863136, "lon": -79.3592942}, {"type": "node", "id": 6778374312, "lat": -2.8864662, "lon": -79.3585053}, {"type": "node", "id": 6778374313, "lat": -2.8863204, "lon": -79.3577235}, {"type": "node", "id": 6778374314, "lat": -2.8857405, "lon": -79.3569879}, {"type": "node", "id": 6778374315, "lat": -2.8851522, "lon": -79.356647}, {"type": "node", "id": 6778374316, "lat": -2.8846362, "lon": -79.3562486}, {"type": "node", "id": 6778374317, "lat": -2.884093, "lon": -79.3558559}, {"type": "node", "id": 6778374318, "lat": -2.883541, "lon": -79.3555829}, {"type": "node", "id": 6778374319, "lat": -2.8829709, "lon": -79.3553364}, {"type": "node", "id": 6778374320, "lat": -2.882464, "lon": -79.3550178}, {"type": "node", "id": 6778374321, "lat": -2.8820293, "lon": -79.3545856}, {"type": "node", "id": 6778374322, "lat": -2.8815315, "lon": -79.3542401}, {"type": "node", "id": 6778374323, "lat": -2.8809343, "lon": -79.3540194}, {"type": "node", "id": 6778374324, "lat": -2.8803821, "lon": -79.3536492}, {"type": "node", "id": 6778374325, "lat": -2.8800739, "lon": -79.35311}, {"type": "node", "id": 6778374326, "lat": -2.8797203, "lon": -79.352541}, {"type": "node", "id": 6778374327, "lat": -2.8792495, "lon": -79.3521583}, {"type": "node", "id": 6778374328, "lat": -2.8787696, "lon": -79.3517414}, {"type": "node", "id": 6778374329, "lat": -2.8783078, "lon": -79.3512918}, {"type": "node", "id": 6778374330, "lat": -2.877882, "lon": -79.3507511}, {"type": "node", "id": 6778374331, "lat": -2.8775737, "lon": -79.3502248}, {"type": "node", "id": 6778374332, "lat": -2.8772654, "lon": -79.3496074}, {"type": "node", "id": 6778374333, "lat": -2.8770746, "lon": -79.349}, {"type": "node", "id": 6778374334, "lat": -2.8769019, "lon": -79.3484157}, {"type": "node", "id": 6778374335, "lat": -2.8766207, "lon": -79.3478517}, {"type": "node", "id": 6778374336, "lat": -2.8764028, "lon": -79.3472634}, {"type": "node", "id": 6778374337, "lat": -2.8761668, "lon": -79.34666}, {"type": "node", "id": 6778374338, "lat": -2.8758857, "lon": -79.346091}, {"type": "node", "id": 6778374339, "lat": -2.8755048, "lon": -79.3453799}, {"type": "node", "id": 6778374340, "lat": -2.8752056, "lon": -79.3448412}, {"type": "node", "id": 6778374341, "lat": -2.8748883, "lon": -79.3443105}, {"type": "node", "id": 6778374342, "lat": -2.8745981, "lon": -79.343724}, {"type": "node", "id": 6778374343, "lat": -2.8742627, "lon": -79.3431764}, {"type": "node", "id": 6778374344, "lat": -2.8738821, "lon": -79.3426693}, {"type": "node", "id": 6778374345, "lat": -2.8734835, "lon": -79.3421775}, {"type": "node", "id": 6778374346, "lat": -2.8732565, "lon": -79.34156}, {"type": "node", "id": 6778374347, "lat": -2.8732376, "lon": -79.3409384}, {"type": "node", "id": 6778374348, "lat": -2.8730105, "lon": -79.340295}, {"type": "node", "id": 6778374349, "lat": -2.8725667, "lon": -79.3398465}, {"type": "node", "id": 6778374350, "lat": -2.8720689, "lon": -79.3394802}, {"type": "node", "id": 6778374351, "lat": -2.8714986, "lon": -79.3391668}, {"type": "node", "id": 6778374352, "lat": -2.8709737, "lon": -79.3388128}, {"type": "node", "id": 6778374353, "lat": -2.8706382, "lon": -79.338259}, {"type": "node", "id": 6778374354, "lat": -2.8705017, "lon": -79.3376162}, {"type": "node", "id": 6778374355, "lat": -2.8716772, "lon": -79.3375594}, {"type": "node", "id": 6778374356, "lat": -2.8725002, "lon": -79.3376166}, {"type": "node", "id": 6778374357, "lat": -2.8733056, "lon": -79.3379882}, {"type": "node", "id": 6778374358, "lat": -2.8741019, "lon": -79.3383395}, {"type": "node", "id": 6778374359, "lat": -2.8749799, "lon": -79.3388846}, {"type": "node", "id": 6778374360, "lat": -2.8756495, "lon": -79.339163}, {"type": "node", "id": 6778374361, "lat": -2.8761203, "lon": -79.3395811}, {"type": "node", "id": 6778374362, "lat": -2.8778484, "lon": -79.3401329}, {"type": "node", "id": 6778374363, "lat": -2.8784731, "lon": -79.340625}, {"type": "node", "id": 6778374364, "lat": -2.8790618, "lon": -79.3412717}, {"type": "node", "id": 6778374365, "lat": -2.8797588, "lon": -79.3416884}, {"type": "node", "id": 6778374366, "lat": -2.8800943, "lon": -79.3423163}, {"type": "node", "id": 6778374367, "lat": -2.8805836, "lon": -79.3429441}, {"type": "node", "id": 6778374368, "lat": -2.8810461, "lon": -79.3438339}, {"type": "node", "id": 6778374369, "lat": -2.8813275, "lon": -79.3446014}, {"type": "node", "id": 6778374370, "lat": -2.8815635, "lon": -79.3451952}, {"type": "node", "id": 6778374371, "lat": -2.8818357, "lon": -79.3457997}, {"type": "node", "id": 6778374372, "lat": -2.8824151, "lon": -79.3462586}, {"type": "node", "id": 6778374373, "lat": -2.8833471, "lon": -79.3466176}, {"type": "node", "id": 6778374374, "lat": -2.8841431, "lon": -79.3467975}, {"type": "node", "id": 6778374375, "lat": -2.885084, "lon": -79.3470575}, {"type": "node", "id": 6778374376, "lat": -2.8858982, "lon": -79.3472312}, {"type": "node", "id": 6778374377, "lat": -2.8866849, "lon": -79.3472126}, {"type": "node", "id": 6778374378, "lat": -2.8875258, "lon": -79.3471069}, {"type": "node", "id": 6778374379, "lat": -2.8884753, "lon": -79.347092}, {"type": "node", "id": 6778374380, "lat": -2.8894701, "lon": -79.3471344}, {"type": "node", "id": 6778374381, "lat": -2.8903746, "lon": -79.3472225}, {"type": "node", "id": 6778374382, "lat": -2.8911159, "lon": -79.3470831}, {"type": "node", "id": 6778374383, "lat": -2.89183, "lon": -79.3468634}, {"type": "node", "id": 6778374384, "lat": -2.8927253, "lon": -79.3468947}, {"type": "node", "id": 6778374385, "lat": -2.8937655, "lon": -79.3470293}, {"type": "node", "id": 6778374386, "lat": -2.8945252, "lon": -79.3470714}, {"type": "node", "id": 6778374387, "lat": -2.8956014, "lon": -79.3471025}, {"type": "node", "id": 6778374388, "lat": -2.8964245, "lon": -79.3472221}, {"type": "node", "id": 6778374389, "lat": -2.8971575, "lon": -79.3475882}, {"type": "node", "id": 6778374390, "lat": -2.8977099, "lon": -79.3481118}, {"type": "node", "id": 6778374391, "lat": -2.8981177, "lon": -79.3486824}, {"type": "node", "id": 6778374392, "lat": -2.8987873, "lon": -79.3489771}, {"type": "node", "id": 6778374393, "lat": -2.8997913, "lon": -79.3490634}, {"type": "node", "id": 6778374394, "lat": -2.9000526, "lon": -79.3484075}, {"type": "node", "id": 6778374395, "lat": -2.899464, "lon": -79.347889}, {"type": "node", "id": 6778374396, "lat": -2.8981781, "lon": -79.3467277}, {"type": "node", "id": 6778374397, "lat": -2.8975898, "lon": -79.3463525}, {"type": "node", "id": 6778374398, "lat": -2.8968836, "lon": -79.345806}, {"type": "node", "id": 6778374399, "lat": -2.896259, "lon": -79.345374}, {"type": "node", "id": 6778374400, "lat": -2.8957701, "lon": -79.3449981}, {"type": "node", "id": 6778374401, "lat": -2.8951819, "lon": -79.3447145}, {"type": "node", "id": 6778374402, "lat": -2.8944038, "lon": -79.3444773}, {"type": "node", "id": 6778374403, "lat": -2.8935533, "lon": -79.3441829}, {"type": "node", "id": 6778374404, "lat": -2.8928204, "lon": -79.3439225}, {"type": "node", "id": 6778374405, "lat": -2.891789, "lon": -79.3435715}, {"type": "node", "id": 6778374406, "lat": -2.8913813, "lon": -79.3430533}, {"type": "node", "id": 6778374407, "lat": -2.8911267, "lon": -79.3420879}, {"type": "node", "id": 6778374408, "lat": -2.8906105, "lon": -79.3415872}, {"type": "node", "id": 6778374409, "lat": -2.8900942, "lon": -79.3410174}, {"type": "node", "id": 6778374410, "lat": -2.8896593, "lon": -79.3404587}, {"type": "node", "id": 6778374411, "lat": -2.8890527, "lon": -79.3399846}, {"type": "node", "id": 6778374412, "lat": -2.888898, "lon": -79.3392889}, {"type": "node", "id": 6778374413, "lat": -2.8896661, "lon": -79.3389044}, {"type": "node", "id": 6778374414, "lat": -2.8900632, "lon": -79.3383658}, {"type": "node", "id": 6778374415, "lat": -2.8908403, "lon": -79.3379746}, {"type": "node", "id": 6778374416, "lat": -2.892097, "lon": -79.3377254}, {"type": "node", "id": 6778374417, "lat": -2.8926025, "lon": -79.3371648}, {"type": "node", "id": 6778374418, "lat": -2.8919781, "lon": -79.3368779}, {"type": "node", "id": 6778374419, "lat": -2.891291, "lon": -79.3369396}, {"type": "node", "id": 6778374420, "lat": -2.890269, "lon": -79.3368809}, {"type": "node", "id": 6778374421, "lat": -2.8896717, "lon": -79.3366091}, {"type": "node", "id": 6778374422, "lat": -2.8890558, "lon": -79.3359343}, {"type": "node", "id": 6778374423, "lat": -2.8884402, "lon": -79.3354608}, {"type": "node", "id": 6778374424, "lat": -2.8876889, "lon": -79.3350077}, {"type": "node", "id": 6778374425, "lat": -2.8867838, "lon": -79.3344491}, {"type": "node", "id": 6778374426, "lat": -2.8876245, "lon": -79.3342517}, {"type": "node", "id": 6778374427, "lat": -2.8884475, "lon": -79.3342803}, {"type": "node", "id": 6778374428, "lat": -2.8892338, "lon": -79.3339795}, {"type": "node", "id": 6778374429, "lat": -2.8897668, "lon": -79.3336235}, {"type": "node", "id": 6778374430, "lat": -2.8902182, "lon": -79.3330961}, {"type": "node", "id": 6778374431, "lat": -2.8901267, "lon": -79.3323711}, {"type": "node", "id": 6778374432, "lat": -2.8892581, "lon": -79.3320851}, {"type": "node", "id": 6778374433, "lat": -2.8882899, "lon": -79.3316627}, {"type": "node", "id": 6778374434, "lat": -2.8877649, "lon": -79.3313672}, {"type": "node", "id": 6778374435, "lat": -2.8871856, "lon": -79.3309689}, {"type": "node", "id": 6778374436, "lat": -2.8865069, "lon": -79.3306821}, {"type": "node", "id": 6778374437, "lat": -2.8860629, "lon": -79.3300621}, {"type": "node", "id": 6778374438, "lat": -2.8868127, "lon": -79.3295163}, {"type": "node", "id": 6778374439, "lat": -2.8872277, "lon": -79.3288771}, {"type": "node", "id": 6778374440, "lat": -2.8872987, "lon": -79.3279118}, {"type": "node", "id": 6778374441, "lat": -2.8866456, "lon": -79.3265614}, {"type": "node", "id": 6778374442, "lat": -2.8876854, "lon": -79.3265026}, {"type": "node", "id": 6778374443, "lat": -2.8883278, "lon": -79.3267551}, {"type": "node", "id": 6778374444, "lat": -2.8889251, "lon": -79.3270381}, {"type": "node", "id": 6778374445, "lat": -2.8894861, "lon": -79.3272633}, {"type": "node", "id": 6778374446, "lat": -2.8900743, "lon": -79.3275064}, {"type": "node", "id": 6778374447, "lat": -2.8906071, "lon": -79.3269767}, {"type": "node", "id": 6778374448, "lat": -2.8899006, "lon": -79.326275}, {"type": "node", "id": 6778374449, "lat": -2.8893752, "lon": -79.325663}, {"type": "node", "id": 6778374450, "lat": -2.8888769, "lon": -79.3250061}, {"type": "node", "id": 6778374451, "lat": -2.888143, "lon": -79.3240549}, {"type": "node", "id": 6778374452, "lat": -2.8873995, "lon": -79.3227294}, {"type": "node", "id": 6778374453, "lat": -2.8870364, "lon": -79.3218001}, {"type": "node", "id": 6778374454, "lat": -2.8863747, "lon": -79.3207353}, {"type": "node", "id": 6778374455, "lat": -2.885704, "lon": -79.319761}, {"type": "node", "id": 6778374456, "lat": -2.8837011, "lon": -79.3167931}, {"type": "node", "id": 6778374457, "lat": -2.8832386, "lon": -79.3158864}, {"type": "node", "id": 6778374458, "lat": -2.8828476, "lon": -79.3144648}, {"type": "node", "id": 6778374459, "lat": -2.8835894, "lon": -79.3146616}, {"type": "node", "id": 6778374460, "lat": -2.8833804, "lon": -79.3139834}, {"type": "node", "id": 6778374461, "lat": -2.8830356, "lon": -79.3131531}, {"type": "node", "id": 6778374462, "lat": -2.8822015, "lon": -79.3117406}, {"type": "node", "id": 6778374463, "lat": -2.8821088, "lon": -79.3102365}, {"type": "node", "id": 6778374464, "lat": -2.8820169, "lon": -79.3092045}, {"type": "node", "id": 6778374465, "lat": -2.8817899, "lon": -79.3085989}, {"type": "node", "id": 6778374466, "lat": -2.8814083, "lon": -79.3074094}, {"type": "node", "id": 6778374467, "lat": -2.8811362, "lon": -79.3068488}, {"type": "node", "id": 6778374468, "lat": -2.8804737, "lon": -79.3053011}, {"type": "node", "id": 6778374469, "lat": -2.8802466, "lon": -79.3046056}, {"type": "node", "id": 6778374474, "lat": -2.8721323, "lon": -79.3007113}, {"type": "node", "id": 6778374475, "lat": -2.8724738, "lon": -79.2974466}, {"type": "node", "id": 6778374478, "lat": -2.869877, "lon": -79.2971887}, {"type": "node", "id": 6778374479, "lat": -2.865739, "lon": -79.2979653}, {"type": "node", "id": 6778374481, "lat": -2.8639861, "lon": -79.29634}, {"type": "node", "id": 6778374482, "lat": -2.8640008, "lon": -79.286095}, {"type": "node", "id": 6778374483, "lat": -2.8768915, "lon": -79.2888154}, {"type": "node", "id": 6778374484, "lat": -2.878125, "lon": -79.2872194}, {"type": "node", "id": 6778374485, "lat": -2.8801256, "lon": -79.2856945}, {"type": "node", "id": 6778374486, "lat": -2.881947, "lon": -79.2850307}, {"type": "node", "id": 6778374488, "lat": -2.8841241, "lon": -79.2842108}, {"type": "node", "id": 6778374489, "lat": -2.8862479, "lon": -79.2821205}, {"type": "node", "id": 6778374490, "lat": -2.8869646, "lon": -79.2822292}, {"type": "node", "id": 6778374491, "lat": -2.8889778, "lon": -79.2811256}, {"type": "node", "id": 6778374494, "lat": -2.8894274, "lon": -79.2811265}, {"type": "node", "id": 6778374495, "lat": -2.8907672, "lon": -79.2810897}, {"type": "node", "id": 6778374496, "lat": -2.8921274, "lon": -79.2804813}, {"type": "node", "id": 6778374497, "lat": -2.8933653, "lon": -79.280228}, {"type": "node", "id": 6778374498, "lat": -2.8949485, "lon": -79.2808871}, {"type": "node", "id": 6778374499, "lat": -2.8953127, "lon": -79.2815733}, {"type": "node", "id": 6778374500, "lat": -2.8958766, "lon": -79.2822339}, {"type": "node", "id": 6778374501, "lat": -2.8965578, "lon": -79.2824858}, {"type": "node", "id": 6778374502, "lat": -2.8972624, "lon": -79.2828799}, {"type": "node", "id": 6778374503, "lat": -2.8981666, "lon": -79.2842014}, {"type": "node", "id": 6778374504, "lat": -2.8994672, "lon": -79.2870592}, {"type": "node", "id": 6778374506, "lat": -2.9012978, "lon": -79.2870291, "tags": {"mountain_pass": "yes", "name": "Soldados - Chaucha"}}, {"type": "node", "id": 6778374507, "lat": -2.9018893, "lon": -79.2866489}, {"type": "node", "id": 6778374510, "lat": -2.9033824, "lon": -79.2858501}, {"type": "node", "id": 6778374514, "lat": -2.9038271, "lon": -79.2858662}, {"type": "node", "id": 6778374516, "lat": -2.9055493, "lon": -79.2853468}, {"type": "node", "id": 6778374517, "lat": -2.9071521, "lon": -79.2842988}, {"type": "node", "id": 6778374518, "lat": -2.9085824, "lon": -79.2829204}, {"type": "node", "id": 6778374521, "lat": -2.9100009, "lon": -79.2800139}, {"type": "node", "id": 6778374524, "lat": -2.9106901, "lon": -79.2751068}, {"type": "node", "id": 6778374525, "lat": -2.9108107, "lon": -79.2747501}, {"type": "node", "id": 6778374526, "lat": -2.9103258, "lon": -79.2739105}, {"type": "node", "id": 6778374527, "lat": -2.9102655, "lon": -79.2729599}, {"type": "node", "id": 6778374529, "lat": -2.9101058, "lon": -79.2716684}, {"type": "node", "id": 6778374530, "lat": -2.9098025, "lon": -79.2711146}, {"type": "node", "id": 6778374531, "lat": -2.9098192, "lon": -79.2708454}, {"type": "node", "id": 6778374532, "lat": -2.9097643, "lon": -79.2704138}, {"type": "node", "id": 6778374535, "lat": -2.9118897, "lon": -79.2671331}, {"type": "node", "id": 6778374545, "lat": -2.9074529, "lon": -79.2632348}, {"type": "node", "id": 6778374546, "lat": -2.9016099, "lon": -79.2615955}, {"type": "node", "id": 6778374548, "lat": -2.9092545, "lon": -79.2573409}, {"type": "node", "id": 6778374551, "lat": -2.91605, "lon": -79.2578778}, {"type": "node", "id": 6778374558, "lat": -2.9239295, "lon": -79.2575688}, {"type": "node", "id": 6778374562, "lat": -2.9254712, "lon": -79.2559047}, {"type": "node", "id": 6778374563, "lat": -2.9257193, "lon": -79.2557324}, {"type": "node", "id": 6778374565, "lat": -2.9278756, "lon": -79.2549243}, {"type": "node", "id": 6778374569, "lat": -2.9296012, "lon": -79.2544015}, {"type": "node", "id": 6778374572, "lat": -2.9317418, "lon": -79.253582}, {"type": "node", "id": 6778374575, "lat": -2.9325514, "lon": -79.2533433}, {"type": "node", "id": 6778374580, "lat": -2.9365206, "lon": -79.251495}, {"type": "node", "id": 6778374581, "lat": -2.9374143, "lon": -79.2505053}, {"type": "node", "id": 6778374582, "lat": -2.939211, "lon": -79.248711}, {"type": "node", "id": 6778374583, "lat": -2.9400515, "lon": -79.2484264}, {"type": "node", "id": 6778374584, "lat": -2.9403943, "lon": -79.2478912}, {"type": "node", "id": 6778374585, "lat": -2.9412343, "lon": -79.2472615}, {"type": "node", "id": 6778374586, "lat": -2.9415951, "lon": -79.24666}, {"type": "node", "id": 6778374587, "lat": -2.9419733, "lon": -79.2456543}, {"type": "node", "id": 6778374588, "lat": -2.9428498, "lon": -79.245287}, {"type": "node", "id": 6778374589, "lat": -2.9430019, "lon": -79.2442226}, {"type": "node", "id": 6778374590, "lat": -2.9440404, "lon": -79.2433485}, {"type": "node", "id": 6778374591, "lat": -2.9450974, "lon": -79.2427336}, {"type": "node", "id": 6778374592, "lat": -2.9460914, "lon": -79.2422784}, {"type": "node", "id": 6778374593, "lat": -2.9469684, "lon": -79.2421629}, {"type": "node", "id": 6778374594, "lat": -2.9478093, "lon": -79.2421447}, {"type": "node", "id": 6778374595, "lat": -2.9490389, "lon": -79.2419809}, {"type": "node", "id": 6778374596, "lat": -2.9500239, "lon": -79.2416173}, {"type": "node", "id": 6778374597, "lat": -2.9508983, "lon": -79.2398283}, {"type": "node", "id": 6778374598, "lat": -2.9505985, "lon": -79.2390069}, {"type": "node", "id": 6778374599, "lat": -2.9499647, "lon": -79.238457}, {"type": "node", "id": 6778374600, "lat": -2.948915, "lon": -79.2380303}, {"type": "node", "id": 6778374601, "lat": -2.9481823, "lon": -79.2378595}, {"type": "node", "id": 6778374602, "lat": -2.9466705, "lon": -79.2368129}, {"type": "node", "id": 6778374603, "lat": -2.945883, "lon": -79.2362812}, {"type": "node", "id": 6778374604, "lat": -2.9448782, "lon": -79.2356335}, {"type": "node", "id": 6778374605, "lat": -2.943981, "lon": -79.2343966}, {"type": "node", "id": 6778374606, "lat": -2.9434917, "lon": -79.233784}, {"type": "node", "id": 6778374607, "lat": -2.9427687, "lon": -79.2340342}, {"type": "node", "id": 6778374608, "lat": -2.9421526, "lon": -79.2332583}, {"type": "node", "id": 6778374609, "lat": -2.9412563, "lon": -79.2326262}, {"type": "node", "id": 6778374610, "lat": -2.9408126, "lon": -79.2321952}, {"type": "node", "id": 6778374611, "lat": -2.9399268, "lon": -79.2324726}, {"type": "node", "id": 6778374612, "lat": -2.9397621, "lon": -79.2312777}, {"type": "node", "id": 6778374613, "lat": -2.9392642, "lon": -79.2308845}, {"type": "node", "id": 6778374614, "lat": -2.9384573, "lon": -79.2295799}, {"type": "node", "id": 6778374615, "lat": -2.9378418, "lon": -79.2292014}, {"type": "node", "id": 6778374616, "lat": -2.9373611, "lon": -79.2282775}, {"type": "node", "id": 6778374617, "lat": -2.9375498, "lon": -79.22757}, {"type": "node", "id": 6778374618, "lat": -2.936716, "lon": -79.2263611}, {"type": "node", "id": 6778374619, "lat": -2.9356854, "lon": -79.2265066}, {"type": "node", "id": 6778374620, "lat": -2.935071, "lon": -79.2268403}, {"type": "node", "id": 6778374621, "lat": -2.9344463, "lon": -79.226363}, {"type": "node", "id": 6778374622, "lat": -2.9334696, "lon": -79.2263015}, {"type": "node", "id": 6778374623, "lat": -2.9327639, "lon": -79.2260958}, {"type": "node", "id": 6778374624, "lat": -2.9320677, "lon": -79.2261396}, {"type": "node", "id": 6778374625, "lat": -2.9312276, "lon": -79.2266986}, {"type": "node", "id": 6778374626, "lat": -2.9303426, "lon": -79.2274161}, {"type": "node", "id": 6778374627, "lat": -2.9297283, "lon": -79.2278274}, {"type": "node", "id": 6778374628, "lat": -2.9282017, "lon": -79.2287972}, {"type": "node", "id": 6778374629, "lat": -2.9278226, "lon": -79.2292745}, {"type": "node", "id": 6778374630, "lat": -2.9266753, "lon": -79.2299475}, {"type": "node", "id": 6778374631, "lat": -2.924886, "lon": -79.2306698}, {"type": "node", "id": 6778374632, "lat": -2.9241904, "lon": -79.2311082}, {"type": "node", "id": 6778374633, "lat": -2.9235666, "lon": -79.2311918}, {"type": "node", "id": 6778374634, "lat": -2.9212262, "lon": -79.2322641}, {"type": "node", "id": 6778374635, "lat": -2.9200596, "lon": -79.2321934}, {"type": "node", "id": 6778374636, "lat": -2.9188029, "lon": -79.2323263}, {"type": "node", "id": 6778374637, "lat": -2.9180068, "lon": -79.2321011}, {"type": "node", "id": 6778374638, "lat": -2.9174272, "lon": -79.2316022}, {"type": "node", "id": 6778374639, "lat": -2.9168473, "lon": -79.2308055}, {"type": "node", "id": 6778374640, "lat": -2.9165652, "lon": -79.2296839}, {"type": "node", "id": 6778374641, "lat": -2.9161029, "lon": -79.2290124}, {"type": "node", "id": 6778374642, "lat": -2.9160835, "lon": -79.2281715}, {"type": "node", "id": 6778374643, "lat": -2.9167895, "lon": -79.2285796}, {"type": "node", "id": 6778374644, "lat": -2.9178025, "lon": -79.2287601}, {"type": "node", "id": 6778374645, "lat": -2.9183987, "lon": -79.2283387}, {"type": "node", "id": 6778374646, "lat": -2.9192933, "lon": -79.2279202}, {"type": "node", "id": 6778374647, "lat": -2.9199983, "lon": -79.2277168}, {"type": "node", "id": 6778374648, "lat": -2.9209635, "lon": -79.2262661}, {"type": "node", "id": 6778374649, "lat": -2.9216147, "lon": -79.2263522}, {"type": "node", "id": 6778374650, "lat": -2.9224644, "lon": -79.2261547}, {"type": "node", "id": 6778374651, "lat": -2.9236568, "lon": -79.2253737}, {"type": "node", "id": 6778374652, "lat": -2.9241078, "lon": -79.2246377}, {"type": "node", "id": 6778374653, "lat": -2.9243143, "lon": -79.223738}, {"type": "node", "id": 6778374654, "lat": -2.9247657, "lon": -79.2232769}, {"type": "node", "id": 6778374655, "lat": -2.9257056, "lon": -79.222923}, {"type": "node", "id": 6778374656, "lat": -2.9253969, "lon": -79.2221208}, {"type": "node", "id": 6778374657, "lat": -2.9257305, "lon": -79.2215446}, {"type": "node", "id": 6778374658, "lat": -2.9262363, "lon": -79.2211537}, {"type": "node", "id": 6778374659, "lat": -2.9271579, "lon": -79.2206593}, {"type": "node", "id": 6778374660, "lat": -2.9278264, "lon": -79.2202794}, {"type": "node", "id": 6778374661, "lat": -2.9283231, "lon": -79.2198547}, {"type": "node", "id": 6778374662, "lat": -2.9291725, "lon": -79.2195032}, {"type": "node", "id": 6778374663, "lat": -2.9293433, "lon": -79.2188767}, {"type": "node", "id": 6778374664, "lat": -2.9288905, "lon": -79.2184603}, {"type": "node", "id": 6778374665, "lat": -2.9277866, "lon": -79.2179961}, {"type": "node", "id": 6778374666, "lat": -2.9271617, "lon": -79.2173709}, {"type": "node", "id": 6778374667, "lat": -2.9261485, "lon": -79.2171426}, {"type": "node", "id": 6778374668, "lat": -2.9253976, "lon": -79.2168627}, {"type": "node", "id": 6778374669, "lat": -2.9252237, "lon": -79.2155723}, {"type": "node", "id": 6778374670, "lat": -2.9247978, "lon": -79.2150491}, {"type": "node", "id": 6778374671, "lat": -2.9241376, "lon": -79.214936}, {"type": "node", "id": 6778374672, "lat": -2.924245, "lon": -79.2142911}, {"type": "node", "id": 6778374673, "lat": -2.9251126, "lon": -79.2139901}, {"type": "node", "id": 6778374674, "lat": -2.926269, "lon": -79.2133194}, {"type": "node", "id": 6778374675, "lat": -2.9272182, "lon": -79.2131268}, {"type": "node", "id": 6778374676, "lat": -2.9275736, "lon": -79.20922}, {"type": "node", "id": 6778374677, "lat": -2.906908, "lon": -79.2127726}, {"type": "node", "id": 6778374678, "lat": -2.9062665, "lon": -79.2131519}, {"type": "node", "id": 6778374679, "lat": -2.9053272, "lon": -79.2138515}, {"type": "node", "id": 6778374680, "lat": -2.9045139, "lon": -79.214144}, {"type": "node", "id": 6778374681, "lat": -2.9035741, "lon": -79.2145817}, {"type": "node", "id": 6778374682, "lat": -2.9023722, "lon": -79.215049}, {"type": "node", "id": 6778374683, "lat": -2.9013777, "lon": -79.2151675}, {"type": "node", "id": 6778374684, "lat": -2.9005642, "lon": -79.2154014}, {"type": "node", "id": 6778374685, "lat": -2.8997415, "lon": -79.2155191}, {"type": "node", "id": 6778374686, "lat": -2.8986926, "lon": -79.2155494}, {"type": "node", "id": 6778374687, "lat": -2.8971732, "lon": -79.2153775}, {"type": "node", "id": 6778374688, "lat": -2.8964945, "lon": -79.2150582}, {"type": "node", "id": 6778374689, "lat": -2.8971338, "lon": -79.2133405}, {"type": "node", "id": 6778374690, "lat": -2.897313, "lon": -79.212293}, {"type": "node", "id": 6778374691, "lat": -2.8971304, "lon": -79.2111876}, {"type": "node", "id": 6778374692, "lat": -2.8967495, "lon": -79.2104603}, {"type": "node", "id": 6778374693, "lat": -2.8965218, "lon": -79.2094427}, {"type": "node", "id": 6778374694, "lat": -2.8962495, "lon": -79.2088029}, {"type": "node", "id": 6778374695, "lat": -2.8961309, "lon": -79.2081628}, {"type": "node", "id": 6778374696, "lat": -2.8959562, "lon": -79.2063009}, {"type": "node", "id": 6778374697, "lat": -2.8959545, "lon": -79.2052823}, {"type": "node", "id": 6778374698, "lat": -2.8958359, "lon": -79.2045844}, {"type": "node", "id": 6778374699, "lat": -2.8955455, "lon": -79.2039154}, {"type": "node", "id": 6778374700, "lat": -2.8951639, "lon": -79.2027811}, {"type": "node", "id": 6778374701, "lat": -2.8947193, "lon": -79.201851}, {"type": "node", "id": 6778374702, "lat": -2.895134, "lon": -79.2010735}, {"type": "node", "id": 6778374703, "lat": -2.8957753, "lon": -79.2006363}, {"type": "node", "id": 6778374704, "lat": -2.8963537, "lon": -79.2004026}, {"type": "node", "id": 6778374705, "lat": -2.8972295, "lon": -79.199557}, {"type": "node", "id": 6778374706, "lat": -2.8978169, "lon": -79.1993234}, {"type": "node", "id": 6778374707, "lat": -2.8986384, "lon": -79.1984783}, {"type": "node", "id": 6778374708, "lat": -2.8991889, "lon": -79.1978372}, {"type": "node", "id": 6778374709, "lat": -2.8994773, "lon": -79.1971965}, {"type": "node", "id": 6778374710, "lat": -2.8998917, "lon": -79.1962358}, {"type": "node", "id": 6778374711, "lat": -2.9005875, "lon": -79.1959435}, {"type": "node", "id": 6778374712, "lat": -2.9014109, "lon": -79.1962626}, {"type": "node", "id": 6778374713, "lat": -2.9020355, "lon": -79.1967315}, {"type": "node", "id": 6778374714, "lat": -2.9024523, "lon": -79.1972256}, {"type": "node", "id": 6778374715, "lat": -2.9035292, "lon": -79.1977185}, {"type": "node", "id": 6778374716, "lat": -2.9042617, "lon": -79.1977752}, {"type": "node", "id": 6778374717, "lat": -2.90494, "lon": -79.1978326}, {"type": "node", "id": 6778374718, "lat": -2.9056363, "lon": -79.1978608}, {"type": "node", "id": 6778374719, "lat": -2.9063415, "lon": -79.1978012}, {"type": "node", "id": 6778374720, "lat": -2.9070102, "lon": -79.1975089}, {"type": "node", "id": 6778374721, "lat": -2.906774, "lon": -79.1968404}, {"type": "node", "id": 6778374722, "lat": -2.9065376, "lon": -79.1960257}, {"type": "node", "id": 6778374723, "lat": -2.9067715, "lon": -79.1952401}, {"type": "node", "id": 6778374724, "lat": -2.906951, "lon": -79.1944248}, {"type": "node", "id": 6778374725, "lat": -2.907067, "lon": -79.1934645}, {"type": "node", "id": 6778374726, "lat": -2.9070652, "lon": -79.1923296}, {"type": "node", "id": 6778374727, "lat": -2.9069737, "lon": -79.1916895}, {"type": "node", "id": 6778374728, "lat": -2.9069455, "lon": -79.1910207}, {"type": "node", "id": 6778374729, "lat": -2.9069983, "lon": -79.1900892}, {"type": "node", "id": 6778374730, "lat": -2.9071782, "lon": -79.1895071}, {"type": "node", "id": 6778374731, "lat": -2.9072311, "lon": -79.1886633}, {"type": "node", "id": 6778374732, "lat": -2.9075558, "lon": -79.1881389}, {"type": "node", "id": 6778374733, "lat": -2.9075541, "lon": -79.1870911}, {"type": "node", "id": 6778374734, "lat": -2.9074352, "lon": -79.1862768}, {"type": "node", "id": 6778374735, "lat": -2.9072255, "lon": -79.1851777}, {"type": "node", "id": 6778374736, "lat": -2.9068174, "lon": -79.1844504}, {"type": "node", "id": 6778374737, "lat": -2.9065805, "lon": -79.1833165}, {"type": "node", "id": 6778374738, "lat": -2.9062268, "lon": -79.1826768}, {"type": "node", "id": 6778374739, "lat": -2.9055285, "lon": -79.1814542}, {"type": "node", "id": 6778374740, "lat": -2.9049133, "lon": -79.1812512}, {"type": "node", "id": 6778374741, "lat": -2.9041262, "lon": -79.1810197}, {"type": "node", "id": 6778374742, "lat": -2.9028961, "lon": -79.1808182}, {"type": "node", "id": 6778374743, "lat": -2.9021996, "lon": -79.1806445}, {"type": "node", "id": 6778374744, "lat": -2.9014669, "lon": -79.1805001}, {"type": "node", "id": 6778374745, "lat": -2.900409, "lon": -79.180531}, {"type": "node", "id": 6778374746, "lat": -2.8994141, "lon": -79.180387}, {"type": "node", "id": 6778374747, "lat": -2.8981029, "lon": -79.1803604}, {"type": "node", "id": 6778374748, "lat": -2.8980109, "lon": -79.1794}, {"type": "node", "id": 6778374749, "lat": -2.8978651, "lon": -79.1786729}, {"type": "node", "id": 6778374750, "lat": -2.8977736, "lon": -79.1780035}, {"type": "node", "id": 6778374751, "lat": -2.8975736, "lon": -79.1773642}, {"type": "node", "id": 6778374752, "lat": -2.8974184, "lon": -79.1764623}, {"type": "node", "id": 6778374753, "lat": -2.8968011, "lon": -79.1749501}, {"type": "node", "id": 6778374754, "lat": -2.8958408, "lon": -79.173846}, {"type": "node", "id": 6778374755, "lat": -2.8958669, "lon": -79.1732057}, {"type": "node", "id": 6778374756, "lat": -2.8956941, "lon": -79.1725658}, {"type": "node", "id": 6778374757, "lat": -2.8955117, "lon": -79.1716353}, {"type": "node", "id": 6778374758, "lat": -2.8952842, "lon": -79.1707267}, {"type": "node", "id": 6778374759, "lat": -2.8950482, "lon": -79.170174}, {"type": "node", "id": 6778374760, "lat": -2.8943232, "lon": -79.1691859}, {"type": "node", "id": 6778374761, "lat": -2.8937347, "lon": -79.1687506}, {"type": "node", "id": 6778374762, "lat": -2.8927115, "lon": -79.1678794}, {"type": "node", "id": 6778374763, "lat": -2.8929095, "lon": -79.167268}, {"type": "node", "id": 6778374764, "lat": -2.8932884, "lon": -79.1667436}, {"type": "node", "id": 6778374765, "lat": -2.8937032, "lon": -79.1660442}, {"type": "node", "id": 6778374766, "lat": -2.8941364, "lon": -79.165491}, {"type": "node", "id": 6778374767, "lat": -2.8946059, "lon": -79.1650535}, {"type": "node", "id": 6778374768, "lat": -2.8951931, "lon": -79.1647619}, {"type": "node", "id": 6778374769, "lat": -2.8957437, "lon": -79.1641501}, {"type": "node", "id": 6778374770, "lat": -2.8961491, "lon": -79.1631888}, {"type": "node", "id": 6778374771, "lat": -2.8962385, "lon": -79.1625777}, {"type": "node", "id": 6778374772, "lat": -2.8965896, "lon": -79.1616171}, {"type": "node", "id": 6778374773, "lat": -2.8969052, "lon": -79.1610927}, {"type": "node", "id": 6778374774, "lat": -2.8974375, "lon": -79.1603352}, {"type": "node", "id": 6778374775, "lat": -2.8976351, "lon": -79.1595497}, {"type": "node", "id": 6778374776, "lat": -2.8975166, "lon": -79.1589389}, {"type": "node", "id": 6778374777, "lat": -2.897316, "lon": -79.1579499}, {"type": "node", "id": 6778374778, "lat": -2.897315, "lon": -79.1573097}, {"type": "node", "id": 6778374779, "lat": -2.8971685, "lon": -79.1561751}, {"type": "node", "id": 6778374780, "lat": -2.8972214, "lon": -79.15536}, {"type": "node", "id": 6778374781, "lat": -2.8971024, "lon": -79.1544586}, {"type": "node", "id": 6778374782, "lat": -2.8966307, "lon": -79.1535965}, {"type": "node", "id": 6778374783, "lat": -2.8854833, "lon": -79.1491308}, {"type": "node", "id": 6778374784, "lat": -2.8591865, "lon": -79.1423912}, {"type": "node", "id": 6778374785, "lat": -2.8444485, "lon": -79.1429331}, {"type": "node", "id": 6778374786, "lat": -2.8438785, "lon": -79.142726}, {"type": "node", "id": 6778374787, "lat": -2.8430732, "lon": -79.1423406}, {"type": "node", "id": 6778374788, "lat": -2.8411732, "lon": -79.141645}, {"type": "node", "id": 6778374789, "lat": -2.8400516, "lon": -79.1414388}, {"type": "node", "id": 6778374790, "lat": -2.839292, "lon": -79.141381}, {"type": "node", "id": 6778374791, "lat": -2.838261, "lon": -79.1412781}, {"type": "node", "id": 6778374792, "lat": -2.8376009, "lon": -79.1412646}, {"type": "node", "id": 6778374793, "lat": -2.836995, "lon": -79.1412357}, {"type": "node", "id": 6778374794, "lat": -2.8348248, "lon": -79.1412218}, {"type": "node", "id": 6778374795, "lat": -2.8341921, "lon": -79.1413346}, {"type": "node", "id": 6778374796, "lat": -2.8337043, "lon": -79.1416867}, {"type": "node", "id": 6778374797, "lat": -2.8331894, "lon": -79.1419922}, {"type": "node", "id": 6778374798, "lat": -2.8325932, "lon": -79.1423225}, {"type": "node", "id": 6778374799, "lat": -2.8319874, "lon": -79.1423336}, {"type": "node", "id": 6778374800, "lat": -2.8313816, "lon": -79.1423654}, {"type": "node", "id": 6778374801, "lat": -2.8307578, "lon": -79.1424395}, {"type": "node", "id": 6778374802, "lat": -2.8302973, "lon": -79.1428415}, {"type": "node", "id": 6778374803, "lat": -2.8300359, "lon": -79.1433843}, {"type": "node", "id": 6778374804, "lat": -2.8298108, "lon": -79.1439434}, {"type": "node", "id": 6778374805, "lat": -2.8296942, "lon": -79.1445506}, {"type": "node", "id": 6778374806, "lat": -2.8285828, "lon": -79.1450644}, {"type": "node", "id": 6778374807, "lat": -2.8283034, "lon": -79.1455948}, {"type": "node", "id": 6778374808, "lat": -2.828232, "lon": -79.1462081}, {"type": "node", "id": 6778374809, "lat": -2.8278711, "lon": -79.1466893}, {"type": "node", "id": 6778374810, "lat": -2.8277185, "lon": -79.1473814}, {"type": "node", "id": 6778374811, "lat": -2.8271582, "lon": -79.1476099}, {"type": "node", "id": 6778374812, "lat": -2.8272225, "lon": -79.1482089}, {"type": "node", "id": 6778374813, "lat": -2.8267529, "lon": -79.148588}, {"type": "node", "id": 6778374814, "lat": -2.8261927, "lon": -79.1488631}, {"type": "node", "id": 6778374815, "lat": -2.8258861, "lon": -79.1493841}, {"type": "node", "id": 6778374816, "lat": -2.8252804, "lon": -79.1494957}, {"type": "node", "id": 6778374817, "lat": -2.8247746, "lon": -79.1498484}, {"type": "node", "id": 6778374818, "lat": -2.8245404, "lon": -79.1504018}, {"type": "node", "id": 6778374819, "lat": -2.8239802, "lon": -79.1506826}, {"type": "node", "id": 6778374820, "lat": -2.8234109, "lon": -79.1508724}, {"type": "node", "id": 6778374821, "lat": -2.822787, "lon": -79.1509009}, {"type": "node", "id": 6778374822, "lat": -2.8222087, "lon": -79.1511463}, {"type": "node", "id": 6778374823, "lat": -2.8220559, "lon": -79.1517311}, {"type": "node", "id": 6778374824, "lat": -2.8213151, "lon": -79.1521723}, {"type": "node", "id": 6778374825, "lat": -2.8207272, "lon": -79.152017}, {"type": "node", "id": 6778374826, "lat": -2.8201122, "lon": -79.1519516}, {"type": "node", "id": 6778374827, "lat": -2.819561, "lon": -79.1521976}, {"type": "node", "id": 6778374828, "lat": -2.8189643, "lon": -79.1522592}, {"type": "node", "id": 6778374829, "lat": -2.8184856, "lon": -79.1526309}, {"type": "node", "id": 6778374830, "lat": -2.8178799, "lon": -79.1527207}, {"type": "node", "id": 6778374831, "lat": -2.8174104, "lon": -79.1531154}, {"type": "node", "id": 6778374832, "lat": -2.8168501, "lon": -79.1533557}, {"type": "node", "id": 6778374833, "lat": -2.8163624, "lon": -79.1537151}, {"type": "node", "id": 6778374834, "lat": -2.8159019, "lon": -79.1541059}, {"type": "node", "id": 6778374835, "lat": -2.8154957, "lon": -79.1545859}, {"type": "node", "id": 6778374836, "lat": -2.8153882, "lon": -79.1551836}, {"type": "node", "id": 6778374837, "lat": -2.8147917, "lon": -79.1553644}, {"type": "node", "id": 6778374838, "lat": -2.8144398, "lon": -79.1558573}, {"type": "node", "id": 6778374839, "lat": -2.8138977, "lon": -79.1561228}, {"type": "node", "id": 6778374840, "lat": -2.813582, "lon": -79.1566387}, {"type": "node", "id": 6778374841, "lat": -2.8135115, "lon": -79.1577669}, {"type": "node", "id": 6778374842, "lat": -2.8128605, "lon": -79.1578218}, {"type": "node", "id": 6778374843, "lat": -2.8122636, "lon": -79.1577649}, {"type": "node", "id": 6778374844, "lat": -2.8116666, "lon": -79.1576248}, {"type": "node", "id": 6778374845, "lat": -2.8110339, "lon": -79.157791}, {"type": "node", "id": 6778374846, "lat": -2.8104827, "lon": -79.1580268}, {"type": "node", "id": 6778374847, "lat": -2.809986, "lon": -79.158412}, {"type": "node", "id": 6778374848, "lat": -2.8095074, "lon": -79.1588062}, {"type": "node", "id": 6778374849, "lat": -2.8093003, "lon": -79.1593736}, {"type": "node", "id": 6778374850, "lat": -2.8087945, "lon": -79.1597285}, {"type": "node", "id": 6778374851, "lat": -2.8080625, "lon": -79.1600135}, {"type": "node", "id": 6778374852, "lat": -2.8073486, "lon": -79.1602973}, {"type": "node", "id": 6778374853, "lat": -2.8069062, "lon": -79.16071}, {"type": "node", "id": 6778374854, "lat": -2.8070699, "lon": -79.1612858}, {"type": "node", "id": 6778374855, "lat": -2.8070528, "lon": -79.1619609}, {"type": "node", "id": 6778374856, "lat": -2.8065742, "lon": -79.1623219}, {"type": "node", "id": 6778374857, "lat": -2.8059502, "lon": -79.1622841}, {"type": "node", "id": 6778374858, "lat": -2.8049004, "lon": -79.1617001}, {"type": "node", "id": 6778374859, "lat": -2.804331, "lon": -79.161923}, {"type": "node", "id": 6778374860, "lat": -2.8036444, "lon": -79.1622922}, {"type": "node", "id": 6778374861, "lat": -2.8030753, "lon": -79.1626466}, {"type": "node", "id": 6778374862, "lat": -2.8025876, "lon": -79.1630042}, {"type": "node", "id": 6778374863, "lat": -2.802489, "lon": -79.163599}, {"type": "node", "id": 6778374864, "lat": -2.8022277, "lon": -79.1641413}, {"type": "node", "id": 6778374865, "lat": -2.8010248, "lon": -79.1640245}, {"type": "node", "id": 6778374866, "lat": -2.8003922, "lon": -79.1642391}, {"type": "node", "id": 6778374867, "lat": -2.7998682, "lon": -79.1645395}, {"type": "node", "id": 6778374868, "lat": -2.7992808, "lon": -79.1647725}, {"type": "node", "id": 6778374869, "lat": -2.7986752, "lon": -79.1649022}, {"type": "node", "id": 6778374870, "lat": -2.7980969, "lon": -79.1651594}, {"type": "node", "id": 6778374871, "lat": -2.7974823, "lon": -79.1653475}, {"type": "node", "id": 6778374872, "lat": -2.7968857, "lon": -79.1654765}, {"type": "node", "id": 6778374873, "lat": -2.79628, "lon": -79.165568}, {"type": "node", "id": 6778374874, "lat": -2.7955568, "lon": -79.1656641}, {"type": "node", "id": 6778374875, "lat": -2.7949785, "lon": -79.1659033}, {"type": "node", "id": 6778374876, "lat": -2.7946628, "lon": -79.1664169}, {"type": "node", "id": 6778374877, "lat": -2.7941206, "lon": -79.1666729}, {"type": "node", "id": 6778374878, "lat": -2.7936427, "lon": -79.1674914}, {"type": "node", "id": 6778374879, "lat": -2.793517, "lon": -79.1680795}, {"type": "node", "id": 6778374880, "lat": -2.7933914, "lon": -79.1687311}, {"type": "node", "id": 6778374881, "lat": -2.7933744, "lon": -79.1693899}, {"type": "node", "id": 6778374882, "lat": -2.7923215, "lon": -79.1784635}, {"type": "node", "id": 6778374883, "lat": -2.7924943, "lon": -79.1790916}, {"type": "node", "id": 6778374884, "lat": -2.7917992, "lon": -79.1798362}, {"type": "node", "id": 6778374885, "lat": -2.7916917, "lon": -79.1804647}, {"type": "node", "id": 6778374886, "lat": -2.791635, "lon": -79.1808496}, {"type": "node", "id": 6778374887, "lat": -2.7915612, "lon": -79.1811633}, {"type": "node", "id": 6778374888, "lat": -2.7915581, "lon": -79.1814832}, {"type": "node", "id": 6778374889, "lat": -2.7914371, "lon": -79.1822044}, {"type": "node", "id": 6778374890, "lat": -2.7910693, "lon": -79.1834189}, {"type": "node", "id": 6778374891, "lat": -2.7908346, "lon": -79.1840617}, {"type": "node", "id": 6778374892, "lat": -2.7905413, "lon": -79.1848621}, {"type": "node", "id": 6778374893, "lat": -2.7902904, "lon": -79.1854118}, {"type": "node", "id": 6778374894, "lat": -2.7899394, "lon": -79.1862619}, {"type": "node", "id": 6778374895, "lat": -2.7895602, "lon": -79.1869981}, {"type": "node", "id": 6778374896, "lat": -2.7893594, "lon": -79.1900809}, {"type": "node", "id": 6778374897, "lat": -2.7895832, "lon": -79.1915104}, {"type": "node", "id": 6778374898, "lat": -2.7898575, "lon": -79.192554}, {"type": "node", "id": 6778374899, "lat": -2.7900306, "lon": -79.1934546}, {"type": "node", "id": 6778374900, "lat": -2.7900886, "lon": -79.1940344}, {"type": "node", "id": 6778374901, "lat": -2.7901325, "lon": -79.1945786}, {"type": "node", "id": 6778374902, "lat": -2.7903245, "lon": -79.1949074}, {"type": "node", "id": 6778374903, "lat": -2.7911943, "lon": -79.1948001}, {"type": "node", "id": 6778374904, "lat": -2.7906478, "lon": -79.1954438}, {"type": "node", "id": 6778374905, "lat": -2.7903604, "lon": -79.1967015}, {"type": "node", "id": 6778374906, "lat": -2.7900184, "lon": -79.1977598}, {"type": "node", "id": 6778374907, "lat": -2.7889259, "lon": -79.1988474}, {"type": "node", "id": 6778374908, "lat": -2.7884111, "lon": -79.1992197}, {"type": "node", "id": 6778374909, "lat": -2.7879237, "lon": -79.199792}, {"type": "node", "id": 6778374910, "lat": -2.787436, "lon": -79.2002216}, {"type": "node", "id": 6778374911, "lat": -2.7868311, "lon": -79.2008228}, {"type": "node", "id": 6778374912, "lat": -2.786091, "lon": -79.2017103}, {"type": "node", "id": 6778374913, "lat": -2.7851425, "lon": -79.2023687}, {"type": "node", "id": 6778374914, "lat": -2.7846821, "lon": -79.2028556}, {"type": "node", "id": 6778374915, "lat": -2.7837334, "lon": -79.2033713}, {"type": "node", "id": 6778374916, "lat": -2.7828117, "lon": -79.2037729}, {"type": "node", "id": 6778374917, "lat": -2.7816909, "lon": -79.2040888}, {"type": "node", "id": 6778374918, "lat": -2.7804611, "lon": -79.2040625}, {"type": "node", "id": 6778374919, "lat": -2.7802173, "lon": -79.1984036}, {"type": "node", "id": 6778374920, "lat": -2.7798725, "lon": -79.1976325}, {"type": "node", "id": 6778374921, "lat": -2.7791582, "lon": -79.1976903}, {"type": "node", "id": 6778374922, "lat": -2.7786058, "lon": -79.1971656}, {"type": "node", "id": 6778374923, "lat": -2.7781711, "lon": -79.196747}, {"type": "node", "id": 6778374924, "lat": -2.7716344, "lon": -79.1856403}, {"type": "node", "id": 6778374925, "lat": -2.7710652, "lon": -79.1858986}, {"type": "node", "id": 6778374926, "lat": -2.7703423, "lon": -79.1862426}, {"type": "node", "id": 6778374927, "lat": -2.7695924, "lon": -79.1866725}, {"type": "node", "id": 6778374928, "lat": -2.7682724, "lon": -79.1867886}, {"type": "node", "id": 6778374929, "lat": -2.7669805, "lon": -79.1875623}, {"type": "node", "id": 6778374930, "lat": -2.7670086, "lon": -79.1881625}, {"type": "node", "id": 6778374931, "lat": -2.7667836, "lon": -79.1888777}, {"type": "node", "id": 6778374932, "lat": -2.7662688, "lon": -79.1893068}, {"type": "node", "id": 6778374933, "lat": -2.7657177, "lon": -79.1896224}, {"type": "node", "id": 6778374934, "lat": -2.7656915, "lon": -79.1902227}, {"type": "node", "id": 6778374935, "lat": -2.7653215, "lon": -79.1907088}, {"type": "node", "id": 6778374936, "lat": -2.764807, "lon": -79.1913098}, {"type": "node", "id": 6778374937, "lat": -2.7639757, "lon": -79.1917113}, {"type": "node", "id": 6778374938, "lat": -2.7633066, "lon": -79.191741}, {"type": "node", "id": 6778374939, "lat": -2.7626738, "lon": -79.191856}, {"type": "node", "id": 6778374940, "lat": -2.7619599, "lon": -79.1921718}, {"type": "node", "id": 6778374941, "lat": -2.7614724, "lon": -79.1926582}, {"type": "node", "id": 6778374942, "lat": -2.7607227, "lon": -79.1932022}, {"type": "node", "id": 6778374943, "lat": -2.759259, "lon": -79.1939761}, {"type": "node", "id": 6778374944, "lat": -2.7586267, "lon": -79.1944345}, {"type": "node", "id": 6778374945, "lat": -2.7582041, "lon": -79.1959785}, {"type": "node", "id": 6778374946, "lat": -2.757718, "lon": -79.1974658}, {"type": "node", "id": 6778374947, "lat": -2.7575475, "lon": -79.1982945}, {"type": "node", "id": 6778374948, "lat": -2.7573766, "lon": -79.1989237}, {"type": "node", "id": 6778374949, "lat": -2.7566039, "lon": -79.202183}, {"type": "node", "id": 6778374950, "lat": -2.756173, "lon": -79.2042131}, {"type": "node", "id": 6778374951, "lat": -2.7560834, "lon": -79.2048135}, {"type": "node", "id": 6778374952, "lat": -2.7561479, "lon": -79.2055564}, {"type": "node", "id": 6778374953, "lat": -2.7554611, "lon": -79.2058436}, {"type": "node", "id": 6778374954, "lat": -2.7547652, "lon": -79.2061014}, {"type": "node", "id": 6778374955, "lat": -2.7538795, "lon": -79.2064462}, {"type": "node", "id": 6778374956, "lat": -2.7533012, "lon": -79.2067325}, {"type": "node", "id": 6778374957, "lat": -2.7524158, "lon": -79.20722}, {"type": "node", "id": 6778374958, "lat": -2.7519283, "lon": -79.2077924}, {"type": "node", "id": 6778374959, "lat": -2.7513508, "lon": -79.2085649}, {"type": "node", "id": 6778374960, "lat": -2.7503476, "lon": -79.2089092}, {"type": "node", "id": 6778374961, "lat": -2.7487665, "lon": -79.2097973}, {"type": "node", "id": 6778374962, "lat": -2.7478171, "lon": -79.2098561}, {"type": "node", "id": 6778374963, "lat": -2.7473297, "lon": -79.2104571}, {"type": "node", "id": 6778374964, "lat": -2.7471316, "lon": -79.2110289}, {"type": "node", "id": 6778374965, "lat": -2.7466172, "lon": -79.2117441}, {"type": "node", "id": 6778374966, "lat": -2.7460223, "lon": -79.2130151}, {"type": "node", "id": 6778374967, "lat": -2.7463311, "lon": -79.21386}, {"type": "node", "id": 6778374968, "lat": -2.746305, "lon": -79.2145744}, {"type": "node", "id": 9764457683, "lat": -2.7890189, "lon": -79.1878206}, {"type": "node", "id": 9764466981, "lat": -2.7890527, "lon": -79.1880447}, {"type": "node", "id": 9764466982, "lat": -2.789462, "lon": -79.1871474}, {"type": "node", "id": 9770055547, "lat": -2.7903869, "lon": -79.1965856}, {"type": "node", "id": 9912773616, "lat": -2.9035806, "lon": -79.2592389}, {"type": "node", "id": 10266078099, "lat": -2.8484181, "lon": -79.1427871}, {"type": "node", "id": 10273654050, "lat": -2.9229565, "lon": -79.2316234}, {"type": "node", "id": 11819385312, "lat": -2.9017159, "lon": -79.2620631}, {"type": "node", "id": 11922299957, "lat": -2.9115402, "lon": -79.2588996}, {"type": "node", "id": 11922299958, "lat": -2.9087935, "lon": -79.2572966}, {"type": "node", "id": 11922299959, "lat": -2.907076, "lon": -79.2592265}, {"type": "node", "id": 11922299960, "lat": -2.9039001, "lon": -79.2621894}, {"type": "node", "id": 11922299961, "lat": -2.9119162, "lon": -79.2665557}, {"type": "node", "id": 11922299962, "lat": -2.9094269, "lon": -79.2783321}, {"type": "node", "id": 11922299963, "lat": -2.9098215, "lon": -79.2816341}, {"type": "node", "id": 11922323172, "lat": -2.8724806, "lon": -79.2991011}, {"type": "node", "id": 11922323173, "lat": -2.876551, "lon": -79.3002228}, {"type": "node", "id": 11922323174, "lat": -2.8619167, "lon": -79.2951376}, {"type": "node", "id": 11922323175, "lat": -2.8572311, "lon": -79.2970201}, {"type": "node", "id": 11922323176, "lat": -2.8616434, "lon": -79.2960641}, {"type": "node", "id": 11922323177, "lat": -2.8600898, "lon": -79.2957473}, {"type": "node", "id": 11922323178, "lat": -2.8616526, "lon": -79.2893021}, {"type": "node", "id": 11922323179, "lat": -2.8585151, "lon": -79.2967746}, {"type": "node", "id": 11922323180, "lat": -2.8700756, "lon": -79.2859424}, {"type": "node", "id": 11922323181, "lat": -2.8847046, "lon": -79.2829922}, {"type": "node", "id": 11922323182, "lat": -2.8833133, "lon": -79.2848941}, {"type": "node", "id": 11922323183, "lat": -2.8838336, "lon": -79.2846292}, {"type": "node", "id": 11922323184, "lat": -2.8983462, "lon": -79.2852429}, {"type": "node", "id": 12004339111, "lat": -2.7769482, "lon": -79.2606991}, {"type": "way", "id": 722624362, "nodes": [6778374968, 6778374967, 6778374966, 6778374965, 6778374964, 6778374963, 6778374962, 6778374961, 6778374960, 6778374959, 6778374958, 6778374957, 6778374956, 6778374955, 6778374954, 6778374953, 6778374952, 6778374951, 6778374950, 6778374949, 6778374948, 6778374947, 6778374946, 6778374945, 6778374944, 6778374943, 6778374942, 6778374941, 6778374940, 6778374939, 6778374938, 6778374937, 6778374936, 6778374935, 6778374934, 6778374933, 6778374932, 6778374931, 6778374930, 6778374929, 6778374928, 6778374927, 6778374926, 6778374925, 6778374924, 6778374923, 6778374922, 6778374921, 6778374920, 6778374919, 6778374918, 6778374917, 6778374916, 6778374915, 6778374914, 6778374913, 6778374912, 6778374911, 6778374910, 6778374909, 6778374908, 6778374907, 6778374906, 6778374905, 9770055547, 6778374904, 6778374903, 6778374902, 6778374901, 6778374900, 6778374899, 6778374898, 6778374897, 6778374896, 9764466981, 9764457683, 9764466982, 6778374895, 6778374894, 6778374893, 6778374892, 6778374891, 6778374890, 6778374889, 6778374888, 6778374887, 6778374886, 6778374885, 6778374884, 6778374883, 6778374882, 6778374881, 6778374880, 6778374879, 6778374878, 6778374877, 6778374876, 6778374875, 6778374874, 6778374873, 6778374872, 6778374871, 6778374870, 6778374869, 6778374868, 6778374867, 6778374866, 6778374865, 6778374864, 6778374863, 6778374862, 6778374861, 6778374860, 6778374859, 6778374858, 6778374857, 6778374856, 6778374855, 6778374854, 6778374853, 6778374852, 6778374851, 6778374850, 6778374849, 6778374848, 6778374847, 6778374846, 6778374845, 6778374844, 6778374843, 6778374842, 6778374841, 6778374840, 6778374839, 6778374838, 6778374837, 6778374836, 6778374835, 6778374834, 6778374833, 6778374832, 6778374831, 6778374830, 6778374829, 6778374828, 6778374827, 6778374826, 6778374825, 6778374824, 6778374823, 6778374822, 6778374821, 6778374820, 6778374819, 6778374818, 6778374817, 6778374816, 6778374815, 6778374814, 6778374813, 6778374812, 6778374811, 6778374810, 6778374809, 6778374808, 6778374807, 6778374806, 6778374805, 6778374804, 6778374803, 6778374802, 6778374801, 6778374800, 6778374799, 6778374798, 6778374797, 6778374796, 6778374795, 6778374794, 6778374793, 6778374792, 6778374791, 6778374790, 6778374789, 6778374788, 6778374787, 6778374786, 6778374785, 10266078099, 6778374784, 6778374783, 6778374782, 6778374781, 6778374780, 6778374779, 6778374778, 6778374777, 6778374776, 6778374775, 6778374774, 6778374773, 6778374772, 6778374771, 6778374770, 6778374769, 6778374768, 6778374767, 6778374766, 6778374765, 6778374764, 6778374763, 6778374762, 6778374761, 6778374760, 6778374759, 6778374758, 6778374757, 6778374756, 6778374755, 6778374754, 6778374753, 6778374752, 6778374751, 6778374750, 6778374749, 6778374748, 6778374747, 6778374746, 6778374745, 6778374744, 6778374743, 6778374742, 6778374741, 6778374740, 6778374739, 6778374738, 6778374737, 6778374736, 6778374735, 6778374734, 6778374733, 6778374732, 6778374731, 6778374730, 6778374729, 6778374728, 6778374727, 6778374726, 6778374725, 6778374724, 6778374723, 6778374722, 6778374721, 6778374720, 6778374719, 6778374718, 6778374717, 6778374716, 6778374715, 6778374714, 6778374713, 6778374712, 6778374711, 6778374710, 6778374709, 6778374708, 6778374707, 6778374706, 6778374705, 6778374704, 6778374703, 6778374702, 6778374701, 6778374700, 6778374699, 6778374698, 6778374697, 6778374696, 6778374695, 6778374694, 6778374693, 6778374692, 6778374691, 6778374690, 6778374689, 6778374688, 6778374687, 6778374686, 6778374685, 6778374684, 6778374683, 6778374682, 6778374681, 6778374680, 6778374679, 6778374678, 6778374677, 6778374676, 6778374675, 6778374674, 6778374673, 6778374672, 6778374671, 6778374670, 6778374669, 6778374668, 6778374667, 6778374666, 6778374665, 6778374664, 6778374663, 6778374662, 6778374661, 6778374660, 6778374659, 6778374658, 6778374657, 6778374656, 6778374655, 6778374654, 6778374653, 6778374652, 6778374651, 6778374650, 6778374649, 6778374648, 6778374647, 6778374646, 6778374645, 6778374644, 6778374643, 6778374642, 6778374641, 6778374640, 6778374639, 6778374638, 6778374637, 6778374636, 6778374635, 6778374634, 10273654050, 6778374633, 6778374632, 6778374631, 6778374630, 6778374629, 6778374628, 6778374627, 6778374626, 6778374625, 6778374624, 6778374623, 6778374622, 6778374621, 6778374620, 6778374619, 6778374618, 6778374617, 6778374616, 6778374615, 6778374614, 6778374613, 6778374612, 6778374611, 6778374610, 6778374609, 6778374608, 6778374607, 6778374606, 6778374605, 6778374604, 6778374603, 6778374602, 6778374601, 6778374600, 6778374599, 6778374598, 6778374597, 6778374596, 6778374595, 6778374594, 6778374593, 6778374592, 6778374591, 6778374590, 6778374589, 6778374588, 6778374587, 6778374586, 6778374585, 6778374584, 6778374583, 6778374582, 794247208, 6778374581, 6778374580, 794246429, 1505886496, 1505886494, 1505886493, 6778374575, 6778374572, 1505886488, 6778374569, 6778374565, 6778374563, 6778374562, 1505886481, 1505886479, 1505886478, 6778374558, 1505886476, 1505886475, 1067953507, 1505886472, 1505886469, 6778374551, 1505886462, 1505886460, 11922299957, 6778374548, 11922299958, 1505886450, 1505886449, 1505886447, 1505886445, 1505886442, 11922299959, 1505886436, 1505886433, 9912773616, 1505886427, 1505886425, 1505886423, 6778374546, 11819385312, 11922299960, 1505886413, 1505886411, 1505886408, 6778374545, 1505886406, 1505886403, 1505886401, 1505886397, 1505886394, 1505886391, 1505886389, 1505886387, 1505886385, 11922299961, 6778374535, 1505886378, 1505886376, 1505886372, 6778374532, 6778374531, 6778374530, 6778374529, 1505886367, 6778374527, 6778374526, 6778374525, 6778374524, 1505886357, 11922299962, 1505886353, 6778374521, 1440344579, 11922299963, 1440344582, 1440344584, 6778374518, 6778374517, 6778374516, 1440344595, 6778374514, 6778374510, 1440344599, 1440344600, 6778374507, 6778374506, 1440344603, 6778374504, 11922323184, 6778374503, 6778374502, 6778374501, 6778374500, 6778374499, 6778374498, 6778374497, 6778374496, 6778374495, 6778374494, 6778374491, 6778374490, 6778374489, 11922323181, 6778374488, 11922323183, 11922323182, 6778374486, 6778374485, 6778374484, 6778374483, 11922323180, 6778374482, 11922323178, 11922323175, 11922323179, 11922323177, 11922323176, 11922323174, 6778374481, 6778374479, 6778374478, 6778374475, 11922323172, 6778374474, 6203419317, 6203419332, 11922323173, 6203419493, 6203419495, 6203419499, 6203419502, 6778374469, 6778374468, 6778374467, 6778374466, 6778374465, 6778374464, 6778374463, 6778374462, 6778374461, 6778374460, 6778374459, 6778374458, 6778374457, 6778374456, 6778374455, 6778374454, 6778374453, 6778374452, 6778374451, 6778374450, 6778374449, 6778374448, 6778374447, 6778374446, 6778374445, 6778374444, 6778374443, 6778374442, 6778374441, 6778374440, 6778374439, 6778374438, 6778374437, 6778374436, 6778374435, 6778374434, 6778374433, 6778374432, 6778374431, 6778374430, 6778374429, 6778374428, 6778374427, 6778374426, 6778374425, 6778374424, 6778374423, 6778374422, 6778374421, 6778374420, 6778374419, 6778374418, 6778374417, 6778374416, 6778374415, 6778374414, 6778374413, 6778374412, 6778374411, 6778374410, 6778374409, 6778374408, 6778374407, 6778374406, 6778374405, 6778374404, 6778374403, 6778374402, 6778374401, 6778374400, 6778374399, 6778374398, 6778374397, 6778374396, 6778374395, 6778374394, 6778374393, 6778374392, 6778374391, 6778374390, 6778374389, 6778374388, 6778374387, 6778374386, 6778374385, 6778374384, 6778374383, 6778374382, 6778374381, 6778374380, 6778374379, 6778374378, 6778374377, 6778374376, 6778374375, 6778374374, 6778374373, 6778374372, 6778374371, 6778374370, 6778374369, 6778374368, 6778374367, 6778374366, 6778374365, 6778374364, 6778374363, 6778374362, 6778374361, 6778374360, 6778374359, 6778374358, 6778374357, 6778374356, 6778374355, 6778374354, 6778374353, 6778374352, 6778374351, 6778374350, 6778374349, 6778374348, 6778374347, 6778374346, 6778374345, 6778374344, 6778374343, 6778374342, 6778374341, 6778374340, 6778374339, 6778374338, 6778374337, 6778374336, 6778374335, 6778374334, 6778374333, 6778374332, 6778374331, 6778374330, 6778374329, 6778374328, 6778374327, 6778374326, 6778374325, 6778374324, 6778374323, 6778374322, 6778374321, 6778374320, 6778374319, 6778374318, 6778374317, 6778374316, 6778374315, 6778374314, 6778374313, 6778374312, 6778374311, 6778374310, 6778374309, 6778374308, 6778374307, 6778374306, 6778374305, 6778374304, 6778374303, 6778374302, 6778374301, 6778374300, 6778374299, 6778374298, 6778374297, 6778374296, 6778374295, 6778374294, 6778374293, 6778374292, 6778374291, 6778374290, 6778374289, 6778374288, 6778374287, 6778374286, 6778374285, 6778374284, 6778374283, 6778374282, 6778374281, 6778374280, 6778374279, 6778374278, 6778374277, 6778374276, 6778374275, 6778374274, 6778374273, 6778374272, 6778374271, 6778374270, 6778374269, 6778374268, 6778374267, 6778374266, 6778374265, 6778374264, 6778374263, 6778374262, 6778374261, 6778374260, 6778374259, 6778374258, 6778374257, 6778374256, 6778374255, 6778374254, 6778374253, 6778374252, 6778374251, 6778374250, 6778374249, 6778374248, 6778374247, 6778374246, 6778374245, 6778374244, 6778374243, 6778374242, 6778374241, 6778374240, 6778374239, 6778374238, 6778374237, 6778374236, 6778374235, 6778374234, 6778374233, 6778374232, 6778374231, 6778374230, 6778374229, 6778374228, 6778374227, 6778374226, 6778374225, 6778374224, 6778374223, 6778374222, 6778374221, 6778374220, 6778374219, 6778374218, 6778374217, 6778374216, 6778374215, 6778374214, 6778374213, 6778374212, 6778374211, 6778374210, 6778374209, 6778374208, 6778374207, 6778374206, 6778374205, 6778374204, 6778374203, 6778374202, 6778374201, 6778374200, 6778374199, 6778374198, 6778374197, 6778374196, 6778374195, 6778374194, 6778374193, 6778374192, 6778374191, 6778374190, 6778374189, 6778374188, 6778374187, 6778374186, 6778374185, 6778374184, 6778374183, 6778374182, 6778374181, 6778374180, 6778374179, 6778374178, 6778374177, 6778374176, 6778374175, 6778374174, 6778374173, 6778374172, 6778374171, 6778374170, 6778374169, 6778374168, 6778374167, 6778374166, 6778374165, 6778374164, 6778374163, 6778374162, 6778374161, 6778374160, 6778374159, 6778374158, 6778374157, 6778374156, 6778374155, 6778374154, 6778374153, 6778374152, 6778374151, 6778374150, 6778374149, 6778374148, 6778374147, 6778374146, 6778374145, 6778374144, 6778374143, 6778374142, 6778374141, 6778374140, 6778374139, 6778374138, 6778374137, 6778374136, 6778374135, 6778374134, 6778374133, 6778374132, 6778374131, 6778374130, 6778374129, 6778374128, 6778374127, 6778374126, 6778374125, 6778374124, 6778374123, 6778374122, 6778374121, 6778374120, 6778374119, 6778374118, 6778374117, 6778374116, 6778374115, 6778374114, 6778374113, 6778374112, 6778374111, 6778374110, 6778374109, 6778374108, 6778374107, 6778374106, 6778374105, 6778374104, 6778374103, 6778374102, 6778374101, 6778374100, 6778374099, 6778374098, 6778374097, 6778374096, 6778374095, 6778374094, 6778374093, 6778374092, 6778374091, 6778374090, 6778374089, 6778374088, 6778374087, 6778374086, 6778374085, 6778374084, 6778374083, 6778374082, 6778374081, 6778374080, 6778374079, 6778374078, 6778374077, 6778374076, 6778374075, 6778374074, 6778374073, 6778374072, 6778374071, 6778374070, 6778374069, 6778374068, 6778374067, 6778374066, 6778374065, 6778374064, 6778374061, 6778374060, 6778374059, 6778374058, 6778374057, 6778374056, 6778374055, 6778374054, 6778374052, 6778374051, 6778374048, 6778374047, 6778374046, 6778374045, 6778374044, 6778374043, 6778374042, 6778374041, 6778374040, 6778374039, 6778374036, 6778374035, 6778374033, 6778374031, 6778374029, 6778374027, 6778374026, 6778374025, 6778374023, 6778374021, 6778374019, 6778374018, 6778374017, 6778374015, 12004339111, 6778374012, 6778374010, 6778374009, 6778374008, 6778374007, 6778374006, 6778374005, 6778374004, 6778374003, 6778374001, 6778374000, 6778373999, 6778373998, 6778373997, 6778373993, 6778373992, 6778373991, 6778373985, 6778360284, 6778360283, 6778360282, 6778360281, 6778360280, 6778360279, 6778360278, 6778360277, 6778360276, 6778360275, 6778360274, 6778360273, 6778360272, 6778360271, 6778360270, 6778360269, 6778360268, 6778360267, 6778360266, 6778360265, 6778360264, 6778360263, 6778360262, 6778360261, 6778360260, 6778360259, 6778360258, 6778360257, 6778360256, 6778360255, 6778360254, 6778360253, 6778360252, 6778360251, 6778360250, 6778360249, 6778360248, 6778360247, 6778360246, 6778360245, 6778360244, 6778360243, 6778360242, 6778360241, 6778360240, 6778360239, 6778360238, 6778360237, 6778360236, 6778360235, 6778360234, 6778360233, 6778360232, 6778360231, 6778360230, 6778360229, 6778360228, 6778360227, 6778360226, 6778360225, 6778360224, 6778374968]}, {"type": "relation", "id": 225636, "members": [{"type": "way", "ref": 722624362, "role": "outer"}], "tags": {"boundary": "national_park", "is_in:country": "Ecuador", "iucn_level": "2", "leisure": "nature_reserve", "name": "Parque Nacional Cajas", "protect_class": "2", "protect_id": "7913", "protection_title": "National Park", "ramsar": "yes", "ramsar_no": "1203", "type": "multipolygon", "url": "http://www.etapa.net.ec/PNC/default.aspx", "wikidata": "Q1295864", "wikipedia": "es:Parque Nacional El Cajas"}}]}